Workbook

Sheet final-->

Sheet combined
A1: Asset ID | B1: Location Address | C1: JEA GIS Object ID | D1: Sewer Maintenance District | E1: County | F1: Best Estimate of Install Date of Station | G1: Year of Install | H1: Electrical Supplier | I1: JEA Actual ADF (GPD) | J1: JEA Design PHF (GPM) | K1: PS Class
A2: BPS-000639 | B2: 2740 CR 210 | C2: 205269 | D2: St Johns Grid | E2: St Johns | F2: 42676 | G2: =F2 -> 42676 | H2: JEA | I2: =MAX(original!I2,piwebapi_edit!I2,car_edit!I2) -> 2861084.5 | J2: =MAX(original!J2,piwebapi_edit!J2,car_edit!J2) -> 7000
A3: BPS-001645 | B3: 4193 OLDFIELD CROSSING | C3: 1729 | D3: South Grid | E3: Duval | F3: 42755 | G3: =F3 -> 42755 | H3: JEA | I3: =MAX(original!I3,piwebapi_edit!I3,car_edit!I3) -> 2714538.5 | J3: =MAX(original!J3,piwebapi_edit!J3,car_edit!J3) -> 9370
A4: BPS-001950 | B4: 4241 SAN CLERC | C4: 16966 | D4: South Grid | E4: Duval | F4: 41143 | G4: =F4 -> 41143 | H4: JEA | I4: =MAX(original!I4,piwebapi_edit!I4,car_edit!I4) -> 932000 | J4: =MAX(original!J4,piwebapi_edit!J4,car_edit!J4) -> 3040
A5: BPS-002867 | B5: 8617 WESTERN WAY | C5: 204646 | D5: South Grid | E5: Duval | F5: 38533 | G5: =F5 -> 38533 | H5: JEA | I5: =MAX(original!I5,piwebapi_edit!I5,car_edit!I5) -> 2827540.5 | J5: =MAX(original!J5,piwebapi_edit!J5,car_edit!J5) -> 5000
A6: BPS-003387 | B6: 106 TWIN CREEKS Dr | C6: 55153 | D6: St Johns Grid | E6: Duval | F6: 39420 | G6: =F6 -> 39420 | H6: JEA | I6: =MAX(original!I6,piwebapi_edit!I6,car_edit!I6) -> 2481327.6 | J6: =MAX(original!J6,piwebapi_edit!J6,car_edit!J6) -> 4400
A7: BPS-004153 | B7: 6850 Energy Center Drive | C7: 256468 | D7: South Grid | E7: Duval | F7: 43635 | G7: =F7 -> 43635 | H7: JEA | I7: =MAX(original!I7,piwebapi_edit!I7,car_edit!I7) -> 166464 | J7: =MAX(original!J7,piwebapi_edit!J7,car_edit!J7) -> 1200
A8: BPS-004187 | B8: 7806 RAMPART RD | C8: 277052 | D8: West Grid | E8: Duval | F8: 44197 | G8: =F8 -> 44197 | H8: JEA | I8: =MAX(original!I8,piwebapi_edit!I8,car_edit!I8) -> 2297937.6 | J8: =MAX(original!J8,piwebapi_edit!J8,car_edit!J8) -> 5000
A9: BPS-004228 | B9: 10477 BRADLEY RD BOOSTER | C9: 1329 | D9: East Grid | E9: Duval | F9: 44319 | G9: =F9 -> 44319 | H9: JEA | I9: =MAX(original!I9,piwebapi_edit!I9,car_edit!I9) -> 12497059 | J9: =MAX(original!J9,piwebapi_edit!J9,car_edit!J9) -> 19500
A10: BPS-004296 | B10: 3742 ROBENA ROAD | C10: 315233 | D10: North Grid | E10: Duval | F10: 45078 | G10: =F10 -> 45078 | H10: JEA | I10: =MAX(original!I10,piwebapi_edit!I10,car_edit!I10) -> 0 | J10: =MAX(original!J10,piwebapi_edit!J10,car_edit!J10) -> 0
A11: BPS-004333 | B11: 85008 ART WILSON LN | C11: 354434 | D11: Nassau Grid | E11: Nassau | F11: 45350 | G11: =F11 -> 45350 | H11: FPL | I11: =MAX(original!I11,piwebapi_edit!I11,car_edit!I11) -> 0 | J11: =MAX(original!J11,piwebapi_edit!J11,car_edit!J11) -> 0
A12: LS-000001 | B12: 12770 1ST ST | C12: 1907 | D12: North Grid | E12: Duval | F12: 25569 | G12: =F12 -> 25569 | H12: JEA | I12: =MAX(original!I12,piwebapi_edit!I12,car_edit!I12) -> 3800.0027 | J12: =MAX(original!J12,piwebapi_edit!J12,car_edit!J12) -> 391.9503
A13: LS-000002 | B13: 2580 1ST ST W | C13: 54481 | D13: North Grid | E13: Duval | F13: 18264 | G13: =F13 -> 18264 | H13: JEA | I13: =MAX(original!I13,piwebapi_edit!I13,car_edit!I13) -> 772.33629 | J13: =MAX(original!J13,piwebapi_edit!J13,car_edit!J13) -> 178.69535
... A1609: LS-004320 | B1609: 1661 RIBAULT SCENIC DRI | C1609: 338033 | D1609: North Grid | E1609: Duval | F1609: 45186 | G1609: =F1609 -> 45186 | H1609: JEA | I1609: =MAX(original!I1609,piwebapi_edit!I1609,car_edit!I1609) -> 0 | J1609: =MAX(original!J1609,piwebapi_edit!J1609,car_edit!J1609) -> 0
A1610: LS-004321 | B1610: 280 Accolade Av | C1610: 338433 | D1610: St Johns Grid | F1610: 45200 | G1610: =F1610 -> 45200 | H1610: FPL | I1610: =MAX(original!I1610,piwebapi_edit!I1610,car_edit!I1610) -> 863.76843 | J1610: =MAX(original!J1610,piwebapi_edit!J1610,car_edit!J1610) -> 249.89378
A1611: LS-004322 | B1611: 8518 BELFORT LANDING | C1611: 340433 | D1611: South Grid | E1611: Duval | F1611: 45202 | G1611: =F1611 -> 45202 | H1611: JEA | I1611: =MAX(original!I1611,piwebapi_edit!I1611,car_edit!I1611) -> 0 | J1611: =MAX(original!J1611,piwebapi_edit!J1611,car_edit!J1611) -> 0
A1612: LS-004323 | B1612: 442 Palm Valley Rd | C1612: 340033 | D1612: St Johns Grid | E1612: St Johns | F1612: 45108 | G1612: =F1612 -> 45108 | H1612: JEA | I1612: =MAX(original!I1612,piwebapi_edit!I1612,car_edit!I1612) -> 1474.8918 | J1612: =MAX(original!J1612,piwebapi_edit!J1612,car_edit!J1612) -> 185.87591
A1613: LS-004324 | B1613: 6811 Myrtle Oaks Road | C1613: 342833 | D1613: North Grid | E1613: Duval | F1613: 45230 | G1613: =F1613 -> 45230 | H1613: JEA | I1613: =MAX(original!I1613,piwebapi_edit!I1613,car_edit!I1613) -> 0 | J1613: =MAX(original!J1613,piwebapi_edit!J1613,car_edit!J1613) -> 0
A1614: LS-004325 | B1614: 12706 WHELAN AVENUE | C1614: 343233 | D1614: North Grid | E1614: Duval | F1614: 45230 | G1614: =F1614 -> 45230 | H1614: JEA | I1614: =MAX(original!I1614,piwebapi_edit!I1614,car_edit!I1614) -> 0 | J1614: =MAX(original!J1614,piwebapi_edit!J1614,car_edit!J1614) -> 0
A1615: LS-004326 | B1615: 10450 BENSON LAKE DR | C1615: 322833 | D1615: West Grid | E1615: Duval | F1615: 45231 | G1615: =F1615 -> 45231 | H1615: JEA | I1615: =MAX(original!I1615,piwebapi_edit!I1615,car_edit!I1615) -> 0 | J1615: =MAX(original!J1615,piwebapi_edit!J1615,car_edit!J1615) -> 0
A1616: LS-004327 | B1616: 4640 Lusso Lane | D1616: East Grid | E1616: Duval | F1616: 45266 | G1616: =F1616 -> 45266 | H1616: JEA | I1616: =MAX(original!I1616,piwebapi_edit!I1616,car_edit!I1616) -> 0 | J1616: =MAX(original!J1616,piwebapi_edit!J1616,car_edit!J1616) -> 0
A1617: LS-004328 | B1617: 98 Bay Lake Drive | C1617: 345634 | D1617: St Johns Grid | E1617: St Johns | F1617: 45258 | G1617: =F1617 -> 45258 | H1617: FPL | I1617: =MAX(original!I1617,piwebapi_edit!I1617,car_edit!I1617) -> 0 | J1617: =MAX(original!J1617,piwebapi_edit!J1617,car_edit!J1617) -> 0
A1618: LS-004329 | B1618: 12607 Percy Creek Drive | C1618: 345234 | D1618: North Grid | E1618: Duval | F1618: 45279 | G1618: =F1618 -> 45279 | H1618: JEA | I1618: =MAX(original!I1618,piwebapi_edit!I1618,car_edit!I1618) -> 0 | J1618: =MAX(original!J1618,piwebapi_edit!J1618,car_edit!J1618) -> 0
A1619: LS-004330 | B1619: 1015 EAST PEYTON PARKWAY | C1619: 346835 | D1619: St Johns Grid | E1619: Duval | F1619: 45372 | G1619: =F1619 -> 45372 | H1619: JEA | I1619: =MAX(original!I1619,piwebapi_edit!I1619,car_edit!I1619) -> 0 | J1619: =MAX(original!J1619,piwebapi_edit!J1619,car_edit!J1619) -> 0
A1620: LS-004331 | B1620: 5420 Tellaro Lane | C1620: 347634 | D1620: West Grid | E1620: Duval | F1620: 45275 | G1620: =F1620 -> 45275 | H1620: JEA | I1620: =MAX(original!I1620,piwebapi_edit!I1620,car_edit!I1620) -> 0 | J1620: =MAX(original!J1620,piwebapi_edit!J1620,car_edit!J1620) -> 0
A1621: LS-004332 | B1621: 6804 Golden Monarch Avenue | C1621: 347635 | D1621: South Grid | E1621: Duval | F1621: 44913 | G1621: =F1621 -> 44913 | H1621: JEA | I1621: =MAX(original!I1621,piwebapi_edit!I1621,car_edit!I1621) -> 0 | J1621: =MAX(original!J1621,piwebapi_edit!J1621,car_edit!J1621) -> 0
A1622: LS-004334 | B1622: 12273 PARKLAND VIEW LANE | C1622: 348434 | D1622: North Grid | E1622: Duval | F1622: 45302 | G1622: =F1622 -> 45302 | H1622: JEA | I1622: =MAX(original!I1622,piwebapi_edit!I1622,car_edit!I1622) -> 0 | J1622: =MAX(original!J1622,piwebapi_edit!J1622,car_edit!J1622) -> 0
A1623: LS-004335 | B1623: 118 PINE CHASE WAY | C1623: 351235 | D1623: St Johns Grid | E1623: St Johns | F1623: 45300 | G1623: =F1623 -> 45300 | H1623: FPL | I1623: =MAX(original!I1623,piwebapi_edit!I1623,car_edit!I1623) -> 0 | J1623: =MAX(original!J1623,piwebapi_edit!J1623,car_edit!J1623) -> 0
A1624: LS-004336 | B1624: 5425 BARTRAM COMMONS DRIVE | C1624: 349234 | D1624: St Johns Grid | E1624: Duval | F1624: 45300 | G1624: =F1624 -> 45300 | H1624: JEA | I1624: =MAX(original!I1624,piwebapi_edit!I1624,car_edit!I1624) -> 0 | J1624: =MAX(original!J1624,piwebapi_edit!J1624,car_edit!J1624) -> 0
A1625: LS-004337 | B1625: 127 SEAPORT BREEZE ROAD | C1625: 349235 | D1625: St Johns Grid | E1625: St Johns | F1625: 45293 | G1625: =F1625 -> 45293 | H1625: JEA | I1625: =MAX(original!I1625,piwebapi_edit!I1625,car_edit!I1625) -> 28658.524 | J1625: =MAX(original!J1625,piwebapi_edit!J1625,car_edit!J1625) -> 265.58975
A1626: LS-004338 | B1626: 5825 ROBITZSCH LANE | C1626: 354435 | D1626: West Grid | E1626: Duval | F1626: 45303 | G1626: =F1626 -> 45303 | H1626: JEA | I1626: =MAX(original!I1626,piwebapi_edit!I1626,car_edit!I1626) -> 0 | J1626: =MAX(original!J1626,piwebapi_edit!J1626,car_edit!J1626) -> 0
A1627: LS-004339 | B1627: 34 OAK PARK DRIVE | C1627: 351234 | D1627: St Johns Grid | E1627: St Johns | F1627: 45308 | G1627: =F1627 -> 45308 | H1627: FPL | I1627: =MAX(original!I1627,piwebapi_edit!I1627,car_edit!I1627) -> 0 | J1627: =MAX(original!J1627,piwebapi_edit!J1627,car_edit!J1627) -> 0
A1628: LS-004340 | B1628: 9375 LATIGIO LANE | C1628: 350834 | D1628: West Grid | E1628: Duval | F1628: 45317 | G1628: =F1628 -> 45317 | H1628: JEA | I1628: =MAX(original!I1628,piwebapi_edit!I1628,car_edit!I1628) -> 0 | J1628: =MAX(original!J1628,piwebapi_edit!J1628,car_edit!J1628) -> 0
... A1674: VAC-000005 | B1674: 1108 BARNWELL RD | C1674: 72143 | D1674: Nassau Grid | E1674: Nassau | F1674: 38931 | G1674: =F1674 -> 38931 | H1674: FPL | I1674: =MAX(original!I1674,piwebapi_edit!I1674,car_edit!I1674) -> 0 | J1674: =MAX(original!J1674,piwebapi_edit!J1674,car_edit!J1674) -> 0

Sheet parts -->

Sheet original
A1: Asset ID | B1: Location Address | C1: JEA GIS Object ID | D1: Sewer Maintenance District | E1: County | F1: Best Estimate of Install Date of Station | G1: Year of Install | H1: Electrical Supplier | I1: JEA Actual ADF (GPD) | J1: JEA Design PHF (GPM) | K1: PS Class
A2: BPS-000639 | B2: 2740 CR 210 | C2: 205269 | D2: St Johns Grid | E2: St Johns | F2: 42676 | G2: =F2 -> 42676 | H2: JEA | I2: =IF(ISNA(VLOOKUP(A2,'[1]Craig Eval'!A:C,3,FALSE)),"",(VLOOKUP(A2,'[1]Craig Eval'!A:C,3,FALSE))*1000) | J2: =IF(ISNA(VLOOKUP(A2,'[1]Craig Eval'!A:M,13,FALSE)),"",VLOOKUP(A2,'[1]Craig Eval'!A:M,13,FALSE)) | K2: 4
A3: BPS-001645 | B3: 4193 OLDFIELD CROSSING | C3: 1729 | D3: South Grid | E3: Duval | F3: 42755 | G3: =F3 -> 42755 | H3: JEA | I3: =IF(ISNA(VLOOKUP(A3,'[1]Craig Eval'!A:C,3,FALSE)),"",(VLOOKUP(A3,'[1]Craig Eval'!A:C,3,FALSE))*1000) | J3: =IF(ISNA(VLOOKUP(A3,'[1]Craig Eval'!A:M,13,FALSE)),"",VLOOKUP(A3,'[1]Craig Eval'!A:M,13,FALSE)) | K3: 4
A4: BPS-001950 | B4: 4241 SAN CLERC | C4: 16966 | D4: South Grid | E4: Duval | F4: 41143 | G4: =F4 -> 41143 | H4: JEA | I4: =IF(ISNA(VLOOKUP(A4,'[1]Craig Eval'!A:C,3,FALSE)),"",(VLOOKUP(A4,'[1]Craig Eval'!A:C,3,FALSE))*1000) -> 24143.567 | J4: =IF(ISNA(VLOOKUP(A4,'[1]Craig Eval'!A:M,13,FALSE)),"",VLOOKUP(A4,'[1]Craig Eval'!A:M,13,FALSE)) -> 69.028726 | K4: 4
A5: BPS-002867 | B5: 8617 WESTERN WAY | C5: 204646 | D5: South Grid | E5: Duval | F5: 38533 | G5: =F5 -> 38533 | H5: JEA | I5: =IF(ISNA(VLOOKUP(A5,'[1]Craig Eval'!A:C,3,FALSE)),"",(VLOOKUP(A5,'[1]Craig Eval'!A:C,3,FALSE))*1000) | J5: =IF(ISNA(VLOOKUP(A5,'[1]Craig Eval'!A:M,13,FALSE)),"",VLOOKUP(A5,'[1]Craig Eval'!A:M,13,FALSE)) | K5: 4
A6: BPS-003387 | B6: 106 TWIN CREEKS Dr | C6: 55153 | D6: St Johns Grid | E6: Duval | F6: 39420 | G6: =F6 -> 39420 | H6: JEA | I6: =IF(ISNA(VLOOKUP(A6,'[1]Craig Eval'!A:C,3,FALSE)),"",(VLOOKUP(A6,'[1]Craig Eval'!A:C,3,FALSE))*1000) | J6: =IF(ISNA(VLOOKUP(A6,'[1]Craig Eval'!A:M,13,FALSE)),"",VLOOKUP(A6,'[1]Craig Eval'!A:M,13,FALSE)) | K6: 4
A7: BPS-004153 | B7: 6850 Energy Center Drive | C7: 256468 | D7: South Grid | E7: Duval | F7: 43635 | G7: =F7 -> 43635 | H7: JEA | I7: =IF(ISNA(VLOOKUP(A7,'[1]Craig Eval'!A:C,3,FALSE)),"",(VLOOKUP(A7,'[1]Craig Eval'!A:C,3,FALSE))*1000) | J7: =IF(ISNA(VLOOKUP(A7,'[1]Craig Eval'!A:M,13,FALSE)),"",VLOOKUP(A7,'[1]Craig Eval'!A:M,13,FALSE)) | K7: 4
A8: BPS-004187 | B8: 7806 RAMPART RD | C8: 277052 | D8: West Grid | E8: Duval | F8: 44197 | G8: =F8 -> 44197 | H8: JEA | I8: =IF(ISNA(VLOOKUP(A8,'[1]Craig Eval'!A:C,3,FALSE)),"",(VLOOKUP(A8,'[1]Craig Eval'!A:C,3,FALSE))*1000) | J8: =IF(ISNA(VLOOKUP(A8,'[1]Craig Eval'!A:M,13,FALSE)),"",VLOOKUP(A8,'[1]Craig Eval'!A:M,13,FALSE)) | K8: 4
A9: BPS-004228 | B9: 10477 BRADLEY RD BOOSTER | C9: 1329 | D9: East Grid | E9: Duval | F9: 44319 | G9: =F9 -> 44319 | H9: JEA | K9: 4
A10: BPS-004296 | B10: 3742 ROBENA ROAD | C10: 315233 | D10: North Grid | E10: Duval | F10: 45078 | G10: =F10 -> 45078 | H10: JEA | K10: 4
A11: BPS-004333 | B11: 85008 ART WILSON LN | C11: 354434 | D11: Nassau Grid | E11: Nassau | F11: 45350 | G11: =F11 -> 45350 | H11: FPL | K11: 4
A12: LS-000001 | B12: 12770 1ST ST | C12: 1907 | D12: North Grid | E12: Duval | F12: 25569 | G12: =F12 -> 25569 | H12: JEA | I12: =IF(ISNA(VLOOKUP(A12,'[1]Craig Eval'!A:C,3,FALSE)),"",(VLOOKUP(A12,'[1]Craig Eval'!A:C,3,FALSE))*1000) | J12: =IF(ISNA(VLOOKUP(A12,'[1]Craig Eval'!A:M,13,FALSE)),"",VLOOKUP(A12,'[1]Craig Eval'!A:M,13,FALSE)) | K12: 1
A13: LS-000002 | B13: 2580 1ST ST W | C13: 54481 | D13: North Grid | E13: Duval | F13: 18264 | G13: =F13 -> 18264 | H13: JEA | I13: =IF(ISNA(VLOOKUP(A13,'[1]Craig Eval'!A:C,3,FALSE)),"",(VLOOKUP(A13,'[1]Craig Eval'!A:C,3,FALSE))*1000) -> 772.33629 | J13: =IF(ISNA(VLOOKUP(A13,'[1]Craig Eval'!A:M,13,FALSE)),"",VLOOKUP(A13,'[1]Craig Eval'!A:M,13,FALSE)) -> 2.3731941 | K13: 1
A14: LS-000004 | B14: 1999 30TH ST W | C14: 1983 | D14: North Grid | E14: Duval | F14: 35431 | G14: =F14 -> 35431 | H14: JEA | I14: =IF(ISNA(VLOOKUP(A14,'[1]Craig Eval'!A:C,3,FALSE)),"",(VLOOKUP(A14,'[1]Craig Eval'!A:C,3,FALSE))*1000) -> 16897.508 | J14: =IF(ISNA(VLOOKUP(A14,'[1]Craig Eval'!A:M,13,FALSE)),"",VLOOKUP(A14,'[1]Craig Eval'!A:M,13,FALSE)) -> 48.977382 | K14: 1
A15: LS-000005 | B15: 94 32ND ST E | C15: 1298 | D15: North Grid | E15: Duval | F15: 34700 | G15: =F15 -> 34700 | H15: JEA | I15: =IF(ISNA(VLOOKUP(A15,'[1]Craig Eval'!A:C,3,FALSE)),"",(VLOOKUP(A15,'[1]Craig Eval'!A:C,3,FALSE))*1000) -> 131570.51 | J15: =IF(ISNA(VLOOKUP(A15,'[1]Craig Eval'!A:M,13,FALSE)),"",VLOOKUP(A15,'[1]Craig Eval'!A:M,13,FALSE)) -> 339.89131 | K15: 4
A16: LS-000006 | B16: 1870 41ST ST W | C16: 1804 | D16: North Grid | E16: Duval | F16: 32143 | G16: =F16 -> 32143 | H16: JEA | I16: =IF(ISNA(VLOOKUP(A16,'[1]Craig Eval'!A:C,3,FALSE)),"",(VLOOKUP(A16,'[1]Craig Eval'!A:C,3,FALSE))*1000) -> 47950.201 | J16: =IF(ISNA(VLOOKUP(A16,'[1]Craig Eval'!A:M,13,FALSE)),"",VLOOKUP(A16,'[1]Craig Eval'!A:M,13,FALSE)) -> 132.64588 | K16: 3
A17: LS-000007 | B17: 1646 45TH ST W | C17: 54482 | D17: North Grid | E17: Duval | F17: 21916 | G17: =F17 -> 21916 | H17: JEA | I17: =IF(ISNA(VLOOKUP(A17,'[1]Craig Eval'!A:C,3,FALSE)),"",(VLOOKUP(A17,'[1]Craig Eval'!A:C,3,FALSE))*1000) -> 25946.152 | J17: =IF(ISNA(VLOOKUP(A17,'[1]Craig Eval'!A:M,13,FALSE)),"",VLOOKUP(A17,'[1]Craig Eval'!A:M,13,FALSE)) -> 73.958138 | K17: 2
A18: LS-000013 | B18: 2809 5TH ST W | C18: 1941 | D18: North Grid | E18: Duval | F18: 21186 | G18: =F18 -> 21186 | H18: JEA | I18: =IF(ISNA(VLOOKUP(A18,'[1]Craig Eval'!A:C,3,FALSE)),"",(VLOOKUP(A18,'[1]Craig Eval'!A:C,3,FALSE))*1000) | J18: =IF(ISNA(VLOOKUP(A18,'[1]Craig Eval'!A:M,13,FALSE)),"",VLOOKUP(A18,'[1]Craig Eval'!A:M,13,FALSE)) | K18: 4
A19: LS-000014 | B19: 5233 5TH ST W | C19: 1940 | D19: West Grid | E19: Duval | F19: 19725 | G19: =F19 -> 19725 | H19: JEA | I19: =IF(ISNA(VLOOKUP(A19,'[1]Craig Eval'!A:C,3,FALSE)),"",(VLOOKUP(A19,'[1]Craig Eval'!A:C,3,FALSE))*1000) | J19: =IF(ISNA(VLOOKUP(A19,'[1]Craig Eval'!A:M,13,FALSE)),"",VLOOKUP(A19,'[1]Craig Eval'!A:M,13,FALSE)) | K19: 4
A20: LS-000017 | B20: 239 68TH ST W | C20: 1534 | D20: North Grid | E20: Duval | F20: 29221 | G20: =F20 -> 29221 | H20: JEA | I20: =IF(ISNA(VLOOKUP(A20,'[1]Craig Eval'!A:C,3,FALSE)),"",(VLOOKUP(A20,'[1]Craig Eval'!A:C,3,FALSE))*1000) -> 6053.0151 | J20: =IF(ISNA(VLOOKUP(A20,'[1]Craig Eval'!A:M,13,FALSE)),"",VLOOKUP(A20,'[1]Craig Eval'!A:M,13,FALSE)) -> 18.0632 | K20: 1
A21: LS-000018 | B21: 7200 AC SKINNER PY | C21: 1710 | D21: South Grid | E21: Duval | F21: 30317 | G21: =F21 -> 30317 | H21: JEA | I21: =IF(ISNA(VLOOKUP(A21,'[1]Craig Eval'!A:C,3,FALSE)),"",(VLOOKUP(A21,'[1]Craig Eval'!A:C,3,FALSE))*1000) -> 243665.13 | J21: =IF(ISNA(VLOOKUP(A21,'[1]Craig Eval'!A:M,13,FALSE)),"",VLOOKUP(A21,'[1]Craig Eval'!A:M,13,FALSE)) -> 595.21011 | K21: 4
A22: LS-000019 | B22: 5640 101ST ST | C22: 1252 | D22: West Grid | E22: Duval | F22: 18264 | G22: =F22 -> 18264 | H22: JEA | I22: =IF(ISNA(VLOOKUP(A22,'[1]Craig Eval'!A:C,3,FALSE)),"",(VLOOKUP(A22,'[1]Craig Eval'!A:C,3,FALSE))*1000) -> 16416.713 | J22: =IF(ISNA(VLOOKUP(A22,'[1]Craig Eval'!A:M,13,FALSE)),"",VLOOKUP(A22,'[1]Craig Eval'!A:M,13,FALSE)) -> 47.63218 | K22: 1
A23: LS-000023 | B23: MAGNOLIA VALLEY DR. 5097 | C23: 85617 | D23: West Grid | E23: Duval | F23: 40162 | G23: =F23 -> 40162 | H23: JEA | I23: =IF(ISNA(VLOOKUP(A23,'[1]Craig Eval'!A:C,3,FALSE)),"",(VLOOKUP(A23,'[1]Craig Eval'!A:C,3,FALSE))*1000) -> 5303.4806 | J23: =IF(ISNA(VLOOKUP(A23,'[1]Craig Eval'!A:M,13,FALSE)),"",VLOOKUP(A23,'[1]Craig Eval'!A:M,13,FALSE)) -> 15.871636 | K23: 1
... A27: LS-000039 | B27: 9902 103RD ST | C27: 1655 | D27: West Grid | E27: Duval | F27: 34335 | G27: =F27 -> 34335 | H27: JEA | I27: =IF(ISNA(VLOOKUP(A27,'[1]Craig Eval'!A:C,3,FALSE)),"",(VLOOKUP(A27,'[1]Craig Eval'!A:C,3,FALSE))*1000) -> 63218.744 | J27: =IF(ISNA(VLOOKUP(A27,'[1]Craig Eval'!A:M,13,FALSE)),"",VLOOKUP(A27,'[1]Craig Eval'!A:M,13,FALSE)) -> 172.07992 | K27: 2
A28: LS-000045 | B28: 5104 118TH ST | C28: 1256 | D28: West Grid | E28: Duval | F28: 26299 | G28: =F28 -> 26299 | H28: JEA | I28: 10595000 | J28: 11100 | K28: 4
A29: LS-000047 | B29: 5823 118TH ST | C29: 12161 | D29: West Grid | E29: Duval | F29: 37846 | G29: =F29 -> 37846 | H29: JEA | I29: =IF(ISNA(VLOOKUP(A29,'[1]Craig Eval'!A:C,3,FALSE)),"",(VLOOKUP(A29,'[1]Craig Eval'!A:C,3,FALSE))*1000) -> 39761.23 | J29: =IF(ISNA(VLOOKUP(A29,'[1]Craig Eval'!A:M,13,FALSE)),"",VLOOKUP(A29,'[1]Craig Eval'!A:M,13,FALSE)) -> 111.09368 | K29: 1
A30: LS-000048 | B30: 8350 118TH ST | C30: 1562 | D30: West Grid | E30: Duval | F30: 36441 | G30: =F30 -> 36441 | H30: JEA | I30: =IF(ISNA(VLOOKUP(A30,'[1]Craig Eval'!A:C,3,FALSE)),"",(VLOOKUP(A30,'[1]Craig Eval'!A:C,3,FALSE))*1000) -> 42912.255 | J30: =IF(ISNA(VLOOKUP(A30,'[1]Craig Eval'!A:M,13,FALSE)),"",VLOOKUP(A30,'[1]Craig Eval'!A:M,13,FALSE)) -> 119.42333 | K30: 1
A31: LS-000057 | B31: 3215 ABBEYFIELD LN | C31: 1139 | D31: East Grid | E31: Duval | F31: 29221 | G31: =F31 -> 29221 | H31: JEA | I31: =IF(ISNA(VLOOKUP(A31,'[1]Craig Eval'!A:C,3,FALSE)),"",(VLOOKUP(A31,'[1]Craig Eval'!A:C,3,FALSE))*1000) -> 147421.87 | J31: =IF(ISNA(VLOOKUP(A31,'[1]Craig Eval'!A:M,13,FALSE)),"",VLOOKUP(A31,'[1]Craig Eval'!A:M,13,FALSE)) -> 377.25553 | K31: 1
A32: LS-000058 | B32: 5180 ABEL LN | C32: 1490 | D32: West Grid | E32: Duval | F32: 26753 | G32: =F32 -> 26753 | H32: JEA | I32: =IF(ISNA(VLOOKUP(A32,'[1]Craig Eval'!A:C,3,FALSE)),"",(VLOOKUP(A32,'[1]Craig Eval'!A:C,3,FALSE))*1000) -> 17986.645 | J32: =IF(ISNA(VLOOKUP(A32,'[1]Craig Eval'!A:M,13,FALSE)),"",VLOOKUP(A32,'[1]Craig Eval'!A:M,13,FALSE)) -> 52.017385 | K32: 1
A33: LS-000060 | B33: 12733 ABESS BV | C33: 1826 | D33: East Grid | E33: Duval | F33: 31778 | G33: =F33 -> 31778 | H33: JEA | I33: =IF(ISNA(VLOOKUP(A33,'[1]Craig Eval'!A:C,3,FALSE)),"",(VLOOKUP(A33,'[1]Craig Eval'!A:C,3,FALSE))*1000) -> 355410.04 | J33: =IF(ISNA(VLOOKUP(A33,'[1]Craig Eval'!A:M,13,FALSE)),"",VLOOKUP(A33,'[1]Craig Eval'!A:M,13,FALSE)) -> 833.93896 | K33: 4
A34: LS-000063 | B34: 8752 ACANTHUS DR | C34: 1564 | D34: West Grid | E34: Duval | F34: 25569 | G34: =F34 -> 25569 | H34: JEA | I34: =IF(ISNA(VLOOKUP(A34,'[1]Craig Eval'!A:C,3,FALSE)),"",(VLOOKUP(A34,'[1]Craig Eval'!A:C,3,FALSE))*1000) -> 196719.25 | J34: =IF(ISNA(VLOOKUP(A34,'[1]Craig Eval'!A:M,13,FALSE)),"",VLOOKUP(A34,'[1]Craig Eval'!A:M,13,FALSE)) -> 490.61794 | K34: 3
A35: LS-000067 | B35: 11933 ACOSTA RD | C35: 1968 | D35: South Grid | E35: Duval | F35: 29221 | G35: =F35 -> 29221 | H35: JEA | I35: =IF(ISNA(VLOOKUP(A35,'[1]Craig Eval'!A:C,3,FALSE)),"",(VLOOKUP(A35,'[1]Craig Eval'!A:C,3,FALSE))*1000) | J35: =IF(ISNA(VLOOKUP(A35,'[1]Craig Eval'!A:M,13,FALSE)),"",VLOOKUP(A35,'[1]Craig Eval'!A:M,13,FALSE)) | K35: 1
A36: LS-000069 | B36: 505 ADDOR LN | C36: 1369 | D36: West Grid | E36: Duval | F36: 33813 | G36: =F36 -> 33813 | H36: JEA | I36: =IF(ISNA(VLOOKUP(A36,'[1]Craig Eval'!A:C,3,FALSE)),"",(VLOOKUP(A36,'[1]Craig Eval'!A:C,3,FALSE))*1000) -> 1532.786 | J36: =IF(ISNA(VLOOKUP(A36,'[1]Craig Eval'!A:M,13,FALSE)),"",VLOOKUP(A36,'[1]Craig Eval'!A:M,13,FALSE)) -> 4.6781078 | K36: 1
A37: LS-000070 | B37: 9374 ADELAID DR | C37: 2241 | D37: West Grid | E37: Duval | F37: 37117 | G37: =F37 -> 37117 | H37: JEA | I37: =IF(ISNA(VLOOKUP(A37,'[1]Craig Eval'!A:C,3,FALSE)),"",(VLOOKUP(A37,'[1]Craig Eval'!A:C,3,FALSE))*1000) -> 91415.151 | J37: =IF(ISNA(VLOOKUP(A37,'[1]Craig Eval'!A:M,13,FALSE)),"",VLOOKUP(A37,'[1]Craig Eval'!A:M,13,FALSE)) -> 242.80845 | K37: 2
A38: LS-000071 | B38: 2844 ADELE RD | C38: 2012 | D38: South Grid | E38: Duval | F38: 29221 | G38: =F38 -> 29221 | H38: JEA | I38: =IF(ISNA(VLOOKUP(A38,'[1]Craig Eval'!A:C,3,FALSE)),"",(VLOOKUP(A38,'[1]Craig Eval'!A:C,3,FALSE))*1000) -> 8177.49 | J38: =IF(ISNA(VLOOKUP(A38,'[1]Craig Eval'!A:M,13,FALSE)),"",VLOOKUP(A38,'[1]Craig Eval'!A:M,13,FALSE)) -> 24.228523 | K38: 1
A39: LS-000073 | B39: 13650 AEROSPACE WAY | C39: 89458 | D39: West Grid | E39: Duval | F39: 31048 | G39: =F39 -> 31048 | H39: JEA | I39: =IF(ISNA(VLOOKUP(A39,'[1]Craig Eval'!A:C,3,FALSE)),"",(VLOOKUP(A39,'[1]Craig Eval'!A:C,3,FALSE))*1000) -> 6798.2711 | J39: =IF(ISNA(VLOOKUP(A39,'[1]Craig Eval'!A:M,13,FALSE)),"",VLOOKUP(A39,'[1]Craig Eval'!A:M,13,FALSE)) -> 20.23344 | K39: 1
A40: LS-000074 | B40: 125 AFTON LN | C40: 1963 | D40: St Johns Grid | E40: Duval | F40: 36039 | G40: =F40 -> 36039 | H40: JEA | I40: =IF(ISNA(VLOOKUP(A40,'[1]Craig Eval'!A:C,3,FALSE)),"",(VLOOKUP(A40,'[1]Craig Eval'!A:C,3,FALSE))*1000) | J40: =IF(ISNA(VLOOKUP(A40,'[1]Craig Eval'!A:M,13,FALSE)),"",VLOOKUP(A40,'[1]Craig Eval'!A:M,13,FALSE)) | K40: 1
... A504: LS-001092 | B504: 7551 HOGAN RD | C504: 1270 | D504: South Grid | E504: Duval | F504: 25569 | G504: =F504 -> 25569 | H504: JEA | I504: =IF(ISNA(VLOOKUP(A504,'[1]Craig Eval'!A:C,3,FALSE)),"",(VLOOKUP(A504,'[1]Craig Eval'!A:C,3,FALSE))*1000) -> 34765.553 | J504: =IF(ISNA(VLOOKUP(A504,'[1]Craig Eval'!A:M,13,FALSE)),"",VLOOKUP(A504,'[1]Craig Eval'!A:M,13,FALSE)) -> 97.786793 | K504: 1
A505: LS-001093 | B505: 7834 HOLIDAY RD S | C505: 1395 | D505: East Grid | E505: Duval | F505: 29830 | G505: =F505 -> 29830 | H505: JEA | I505: 1183000 | J505: 2400 | K505: 4
A506: LS-001094 | B506: 3655 HOLLY GROVE AV | C506: 17291 | D506: South Grid | E506: Duval | F506: 33161 | G506: =F506 -> 33161 | H506: JEA | I506: =IF(ISNA(VLOOKUP(A506,'[1]Craig Eval'!A:C,3,FALSE)),"",(VLOOKUP(A506,'[1]Craig Eval'!A:C,3,FALSE))*1000) -> 6783.1955 | J506: =IF(ISNA(VLOOKUP(A506,'[1]Craig Eval'!A:M,13,FALSE)),"",VLOOKUP(A506,'[1]Craig Eval'!A:M,13,FALSE)) -> 20.189622 | K506: 1
A507: LS-001095 | B507: 9846 FT CAROLINE RD | C507: 21121 | D507: East Grid | E507: Duval | F507: 35142 | G507: =F507 -> 35142 | H507: JEA | I507: =IF(ISNA(VLOOKUP(A507,'[1]Craig Eval'!A:C,3,FALSE)),"",(VLOOKUP(A507,'[1]Craig Eval'!A:C,3,FALSE))*1000) -> 186300.28 | J507: =IF(ISNA(VLOOKUP(A507,'[1]Craig Eval'!A:M,13,FALSE)),"",VLOOKUP(A507,'[1]Craig Eval'!A:M,13,FALSE)) -> 466.98567 | K507: 1
A508: LS-001096 | B508: 1945 HOLLY OAKS RAVINE DR | C508: 18244 | D508: East Grid | E508: Duval | F508: 24400 | G508: =F508 -> 24400 | H508: JEA | I508: =IF(ISNA(VLOOKUP(A508,'[1]Craig Eval'!A:C,3,FALSE)),"",(VLOOKUP(A508,'[1]Craig Eval'!A:C,3,FALSE))*1000) -> 26914.428 | J508: =IF(ISNA(VLOOKUP(A508,'[1]Craig Eval'!A:M,13,FALSE)),"",VLOOKUP(A508,'[1]Craig Eval'!A:M,13,FALSE)) -> 76.597223 | K508: 1
A509: LS-001097 | B509: 147 HOLLYBERRY LN | C509: 77554 | D509: St Johns Grid | E509: St Johns | F509: 38378 | G509: =F509 -> 38378 | H509: FPL | I509: =IF(ISNA(VLOOKUP(A509,'[1]Craig Eval'!A:C,3,FALSE)),"",(VLOOKUP(A509,'[1]Craig Eval'!A:C,3,FALSE))*1000) | J509: =IF(ISNA(VLOOKUP(A509,'[1]Craig Eval'!A:M,13,FALSE)),"",VLOOKUP(A509,'[1]Craig Eval'!A:M,13,FALSE)) | K509: 1
A510: LS-001098 | B510: 210 HOLLYBROOK AV | C510: 1684 | D510: North Grid | E510: Duval | F510: 24108 | G510: =F510 -> 24108 | H510: JEA | I510: =IF(ISNA(VLOOKUP(A510,'[1]Craig Eval'!A:C,3,FALSE)),"",(VLOOKUP(A510,'[1]Craig Eval'!A:C,3,FALSE))*1000) | J510: =IF(ISNA(VLOOKUP(A510,'[1]Craig Eval'!A:M,13,FALSE)),"",VLOOKUP(A510,'[1]Craig Eval'!A:M,13,FALSE)) | K510: 4
A511: LS-001099 | B511: 7871 HOLLYRIDGE RD | C511: 1178 | D511: South Grid | E511: Duval | F511: 42005 | G511: =F511 -> 42005 | H511: JEA | I511: =IF(ISNA(VLOOKUP(A511,'[1]Craig Eval'!A:C,3,FALSE)),"",(VLOOKUP(A511,'[1]Craig Eval'!A:C,3,FALSE))*1000) -> 26930.704 | J511: =IF(ISNA(VLOOKUP(A511,'[1]Craig Eval'!A:M,13,FALSE)),"",VLOOKUP(A511,'[1]Craig Eval'!A:M,13,FALSE)) -> 76.641533 | K511: 1
A512: LS-001100 | B512: 10220 HOMARD BV N | C512: 27553 | D512: East Grid | E512: Duval | F512: 33023 | G512: =F512 -> 33023 | H512: JEA | I512: =IF(ISNA(VLOOKUP(A512,'[1]Craig Eval'!A:C,3,FALSE)),"",(VLOOKUP(A512,'[1]Craig Eval'!A:C,3,FALSE))*1000) -> 7163.6272 | J512: =IF(ISNA(VLOOKUP(A512,'[1]Craig Eval'!A:M,13,FALSE)),"",VLOOKUP(A512,'[1]Craig Eval'!A:M,13,FALSE)) -> 21.294351 | K512: 1
A513: LS-001101 | B513: 2230 HOME PARK CR E | C513: 159476 | D513: East Grid | E513: Duval | F513: 41134 | G513: =F513 -> 41134 | H513: JEA | I513: =IF(ISNA(VLOOKUP(A513,'[1]Craig Eval'!A:C,3,FALSE)),"",(VLOOKUP(A513,'[1]Craig Eval'!A:C,3,FALSE))*1000) -> 1828.9983 | J513: =IF(ISNA(VLOOKUP(A513,'[1]Craig Eval'!A:M,13,FALSE)),"",VLOOKUP(A513,'[1]Craig Eval'!A:M,13,FALSE)) -> 5.570233 | K513: 1
A514: LS-001103 | B514: 11861 HOOD LANDING RD | C514: 199844 | D514: South Grid | E514: Duval | F514: 32874 | G514: =F514 -> 32874 | H514: JEA | I514: =IF(ISNA(VLOOKUP(A514,'[1]Craig Eval'!A:C,3,FALSE)),"",(VLOOKUP(A514,'[1]Craig Eval'!A:C,3,FALSE))*1000) | J514: =IF(ISNA(VLOOKUP(A514,'[1]Craig Eval'!A:M,13,FALSE)),"",VLOOKUP(A514,'[1]Craig Eval'!A:M,13,FALSE)) | K514: 2
A515: LS-001104 | B515: 12403 HOOD LANDING RD | C515: 1200 | D515: South Grid | E515: Duval | F515: 29221 | G515: =F515 -> 29221 | H515: JEA | I515: =IF(ISNA(VLOOKUP(A515,'[1]Craig Eval'!A:C,3,FALSE)),"",(VLOOKUP(A515,'[1]Craig Eval'!A:C,3,FALSE))*1000) | J515: =IF(ISNA(VLOOKUP(A515,'[1]Craig Eval'!A:M,13,FALSE)),"",VLOOKUP(A515,'[1]Craig Eval'!A:M,13,FALSE)) | K515: 1
A516: LS-001105 | B516: 10142 HOOD RD | C516: 1064 | D516: South Grid | E516: Duval | F516: 31048 | G516: =F516 -> 31048 | H516: JEA | I516: =IF(ISNA(VLOOKUP(A516,'[1]Craig Eval'!A:C,3,FALSE)),"",(VLOOKUP(A516,'[1]Craig Eval'!A:C,3,FALSE))*1000) | J516: =IF(ISNA(VLOOKUP(A516,'[1]Craig Eval'!A:M,13,FALSE)),"",VLOOKUP(A516,'[1]Craig Eval'!A:M,13,FALSE)) | K516: 2
A517: LS-001109 | B517: 2123 HOVINGTON CR W | C517: 1999 | D517: East Grid | E517: Duval | F517: 29952 | G517: =F517 -> 29952 | H517: JEA | I517: =IF(ISNA(VLOOKUP(A517,'[1]Craig Eval'!A:C,3,FALSE)),"",(VLOOKUP(A517,'[1]Craig Eval'!A:C,3,FALSE))*1000) -> 49834.592 | J517: =IF(ISNA(VLOOKUP(A517,'[1]Craig Eval'!A:M,13,FALSE)),"",VLOOKUP(A517,'[1]Craig Eval'!A:M,13,FALSE)) -> 137.56306 | K517: 1
... A1458: LS-004166 | B1458: 1000 Island Point Dr. | C1458: 1875 | D1458: North Grid | E1458: Duval | F1458: 43800 | G1458: =F1458 -> 43800 | H1458: JEA | I1458: =IF(ISNA(VLOOKUP(A1458,'[1]Craig Eval'!A:C,3,FALSE)),"",(VLOOKUP(A1458,'[1]Craig Eval'!A:C,3,FALSE))*1000) | J1458: =IF(ISNA(VLOOKUP(A1458,'[1]Craig Eval'!A:M,13,FALSE)),"",VLOOKUP(A1458,'[1]Craig Eval'!A:M,13,FALSE)) | K1458: 1
A1459: LS-004167 | B1459: 77040 ROBERT WILLIAMS DR | C1459: 264452 | D1459: Nassau Grid | E1459: Nassau | F1459: 43771 | G1459: =F1459 -> 43771 | H1459: FPL | K1459: 1
A1460: LS-004168 | B1460: 11422 MADELYNN DR | C1460: 268004 | D1460: South Grid | E1460: Duval | F1460: 43772 | G1460: =F1460 -> 43772 | H1460: JEA | K1460: 1
A1461: LS-004169 | B1461: 13206 Spartina Grass Dr. | C1461: 262548 | D1461: North Grid | E1461: Duval | F1461: 43773 | G1461: =F1461 -> 43773 | H1461: JEA | K1461: 1
A1462: LS-004170 | B1462: 85633 FALL RIVER PY | C1462: 257140 | D1462: Nassau Grid | E1462: Nassau | F1462: 43774 | G1462: =F1462 -> 43774 | H1462: FPL | K1462: 1
A1463: LS-004171 | B1463: 11399 SQUARE ST | C1463: 260292 | D1463: South Grid | E1463: Duval | F1463: 43775 | G1463: =F1463 -> 43775 | H1463: JEA | K1463: 2
A1464: LS-004172 | B1464: 409 Bartram Market Dr. | C1464: 262564 | D1464: St Johns Grid | E1464: St Johns | F1464: 43801 | G1464: =F1464 -> 43801 | H1464: JEA | K1464: 1
A1465: LS-004173 | B1465: 10335 RIVERWALK CT | C1465: 255828 | D1465: North Grid | E1465: Duval | F1465: 43800 | G1465: =F1465 -> 43800 | H1465: JEA | K1465: 1
A1466: LS-004174 | B1466: 97 WHITE CYPRESS DR | C1466: 266068 | D1466: St Johns Grid | E1466: Duval | F1466: 43800 | G1466: =F1466 -> 43800 | H1466: JEA | K1466: 1
A1467: LS-004175 | B1467: 7736 POINT MEADOWS DR | C1467: 270532 | D1467: South Grid | E1467: Duval | F1467: 43800 | G1467: =F1467 -> 43800 | H1467: JEA | K1467: 1
A1468: LS-004176 | B1468: 80 ANDESITE TL | C1468: 259972 | D1468: St Johns Grid | E1468: St Johns | F1468: 43800 | G1468: =F1468 -> 43800 | H1468: FPL | K1468: 1
A1469: LS-004177 | B1469: 6656 Sandler Lakes Dr | C1469: 265092 | D1469: West Grid | E1469: Duval | F1469: 43949 | G1469: =F1469 -> 43949 | H1469: JEA | K1469: 1
A1470: LS-004178 | B1470: 1966 CARTER LANDING BV | C1470: 265732 | D1470: West Grid | E1470: Duval | F1470: 43885 | G1470: =F1470 -> 43885 | H1470: JEA | K1470: 1
... A1528: LS-004238 | B1528: 424 Burbank Ave. | C1528: 284074 | D1528: St Johns Grid | E1528: St Johns | F1528: 44431 | G1528: =F1528 -> 44431 | H1528: JEA | K1528: 2
A1529: LS-004239 | B1529: 1400 Tan Tara Tr | C1529: 284073 | D1529: West Grid | E1529: Duval | F1529: 44434 | G1529: =F1529 -> 44434 | H1529: JEA
A1530: LS-004240 | B1530: 330 Floco Av | C1530: 284072 | D1530: Nassau Grid | E1530: Nassau | F1530: 44453 | G1530: =F1530 -> 44453 | H1530: FPL | K1530: 1
A1531: LS-004241 | B1531: 452 Cherry Ridge Dr | C1531: 284071 | D1531: West Grid | E1531: Clay | F1531: 44476 | G1531: =F1531 -> 44476 | H1531: CLAY E | K1531: 1
A1532: LS-004242 | B1532: 4965 Waning Way | C1532: 284070 | D1532: South Grid | E1532: Duval | F1532: 44494 | G1532: =F1532 -> 44494 | H1532: JEA | K1532: 1
A1533: LS-004243 | B1533: 13591 Brookwater Dr. | C1533: 284069 | D1533: St Johns Grid | E1533: Duval | F1533: 44504 | G1533: =F1533 -> 44504 | H1533: JEA | K1533: 1
A1534: LS-004244 | B1534: 2189 Hudson Grove Dr | C1534: 284068 | D1534: North Grid | E1534: Duval | F1534: 44504 | G1534: =F1534 -> 44504 | H1534: JEA | K1534: 1
A1535: LS-004245 | B1535: 10481 Anthem Wy | C1535: 284067 | D1535: South Grid | E1535: Duval | F1535: 44531 | G1535: =F1535 -> 44531 | H1535: JEA | K1535: 1
A1536: LS-004246 | B1536: 225 Valley Falls | C1536: 283764 | D1536: St Johns Grid | E1536: Duval | F1536: 44531 | G1536: =F1536 -> 44531 | H1536: JEA
A1537: LS-004247 | B1537: 13095 HOLSINGER BV | C1537: 284066 | D1537: St Johns Grid | E1537: Duval | F1537: 44621 | G1537: =F1537 -> 44621 | H1537: JEA
A1538: LS-004248 | B1538: 372 SAINT ELIZABETH WY | C1538: 284065 | D1538: St Johns Grid | E1538: Duval | F1538: 44622 | G1538: =F1538 -> 44622 | H1538: JEA
A1539: LS-004249 | B1539: 9878 Filament Bv | C1539: 284078 | D1539: South Grid | E1539: Duval | F1539: 44635 | G1539: =F1539 -> 44635 | H1539: JEA | K1539: 1?
A1540: LS-004250 | B1540: 11245 Assembly St | C1540: 284084 | D1540: South Grid | E1540: Duval | F1540: 44636 | G1540: =F1540 -> 44636 | H1540: JEA | K1540: 1
A1541: LS-004251 | B1541: 2293 Kistlers Ridge Wy | C1541: 285013 | D1541: West Grid | E1541: Duval | F1541: 44652 | G1541: =F1541 -> 44652 | H1541: JEA
A1542: LS-004252 | B1542: 1071 Brown Bear Run | C1542: 285012 | D1542: St Johns Grid | E1542: St Johns | F1542: 44652 | G1542: =F1542 -> 44652 | H1542: FPL | K1542: 1
A1543: LS-004253 | B1543: 6349 MORNING BLUFF DR | C1543: 286004 | D1543: WEST | E1543: Duval | F1543: 44682 | G1543: =F1543 -> 44682 | H1543: JEA | K1543: 1
A1544: LS-004254 | B1544: 3771 SPRING GARDEN CT | C1544: 286629 | D1544: South Grid | E1544: Duval | F1544: 44687 | G1544: =F1544 -> 44687 | H1544: JEA | K1544: 1
A1545: LS-004255 | B1545: 151 JULBILEE CIRCLE | C1545: 286628 | D1545: Nassau Grid | E1545: Nassau | F1545: 44687 | G1545: =F1545 -> 44687 | H1545: FPL | K1545: 1
A1546: LS-004256 | B1546: 87 Pasadena Dr | C1546: 286613 | D1546: St Johns Grid | E1546: St Johns | F1546: 44691 | G1546: =F1546 -> 44691 | H1546: FPL | K1546: 1
A1547: LS-004257 | B1547: 237 TERRAPIN CT | C1547: 286948 | D1547: NORTH | E1547: Duval | F1547: 44713 | G1547: =F1547 -> 44713 | H1547: JEA | K1547: 1
A1548: LS-004258 | B1548: 10503 FLORENCE JEAN DR | C1548: 286949 | D1548: SOUTH | E1548: Duval | F1548: 44714 | G1548: =F1548 -> 44714 | H1548: JEA | K1548: 1
A1549: LS-004259 | B1549: 9833 CRAVEN RD | C1549: 288980 | D1549: SOUTH | E1549: Duval | F1549: 44715 | G1549: =F1549 -> 44715 | H1549: JEA | K1549: 1
A1550: LS-004260 | B1550: 26 ROSEMONT DR | C1550: 287252 | D1550: ST JOHNS | E1550: St Johns | F1550: 44716 | G1550: =F1550 -> 44716 | H1550: FPL | K1550: 1
A1551: LS-004261 | B1551: 2026 RIBAULT SCENIC DR | C1551: 287268 | D1551: NORTH | E1551: Duval | F1551: 44717 | G1551: =F1551 -> 44717 | H1551: JEA | K1551: 2
A1552: LS-004262 | B1552: 65980 EDGEWATER DR | C1552: 287572 | D1552: NASSAU | E1552: Nassau | F1552: 44718 | G1552: =F1552 -> 44718 | H1552: FPL | K1552: 1
A1553: LS-004263 | B1553: 29 Cypress Edge Drive | C1553: 288212 | D1553: St Johns Grid | E1553: St Johns | F1553: 44719 | G1553: =F1553 -> 44719 | H1553: FPL | K1553: 2
... A1563: LS-004273 | B1563: 2410 Sapp Road | C1563: 289631 | D1563: North Grid | E1563: Duval | F1563: 44805 | G1563: =F1563 -> 44805 | H1563: JEA | K1563: 1
A1564: LS-004274 | B1564: 95421 Katherine Street | C1564: 293231 | D1564: NASSAU | E1564: Nassau | F1564: 44868 | G1564: =F1564 -> 44868 | H1564: FPL
A1565: LS-004275 | B1565: 3766 JONES ROAD | C1565: 296432 | D1565: West Grid | E1565: Duval | F1565: 44916 | G1565: =F1565 -> 44916 | H1565: JEA | K1565: 1
A1566: LS-004276 | B1566: 292 A1A N | C1566: 298433 | D1566: St Johns Grid | E1566: St Johns | F1566: 44924 | G1566: =F1566 -> 44924 | H1566: FPL | K1566: 1
A1567: LS-004277 | B1567: 11229 DOMAIN DRIVE | C1567: 298434 | D1567: South Grid | E1567: Duval | F1567: 44945 | G1567: =F1567 -> 44945 | H1567: JEA | K1567: 2
A1568: LS-004278 | B1568: 104 BEE BALM LANE | C1568: 301633 | D1568: St Johns Grid | E1568: St Johns | F1568: 44946 | G1568: =F1568 -> 44946 | H1568: FPL | K1568: 1
A1569: LS-004279 | B1569: 213 WAMBAW DRIVE | C1569: 301635 | D1569: St Johns Grid | E1569: St Johns | F1569: 44958 | G1569: =F1569 -> 44958 | H1569: FPL | K1569: 1
A1570: LS-004280 | B1570: 257 STORYBOOK POINT | C1570: 301634 | D1570: St Johns Grid | E1570: St Johns | F1570: 44946 | G1570: =F1570 -> 44946 | H1570: FPL | K1570: 1
A1571: LS-004281 | B1571: 12921 DUVAL ROAD | C1571: 302433 | D1571: North Grid | E1571: Duval | F1571: 44951 | G1571: =F1571 -> 44951 | H1571: JEA | K1571: 1
A1572: LS-004282 | B1572: 1511 Zoo Parkway | C1572: 304433 | D1572: North Grid | E1572: Duval | F1572: 44970 | G1572: =F1572 -> 44970 | H1572: JEA | K1572: 1
...

Sheet piwebapi_edit
A1: Asset ID | B1: Location Address | C1: JEA GIS Object ID | D1: Sewer Maintenance District | E1: County | F1: Best Estimate of Install Date of Station | G1: Year of Install | H1: Electrical Supplier | I1: JEA Actual ADF (GPD) | J1: JEA Design PHF (GPM) | K1: PS Class
A2: BPS-000639 | B2: 2740 CR 210 | C2: 205269 | D2: St Johns Grid | E2: St Johns | F2: 42676 | G2: =F2 -> 42676 | H2: JEA | K2: 4
A3: BPS-001645 | B3: 4193 OLDFIELD CROSSING | C3: 1729 | D3: South Grid | E3: Duval | F3: 42755 | G3: =F3 -> 42755 | H3: JEA | K3: 4
A4: BPS-001950 | B4: 4241 SAN CLERC | C4: 16966 | D4: South Grid | E4: Duval | F4: 41143 | G4: =F4 -> 41143 | H4: JEA | K4: 4
A5: BPS-002867 | B5: 8617 WESTERN WAY | C5: 204646 | D5: South Grid | E5: Duval | F5: 38533 | G5: =F5 -> 38533 | H5: JEA | K5: 4
A6: BPS-003387 | B6: 106 TWIN CREEKS Dr | C6: 55153 | D6: St Johns Grid | E6: Duval | F6: 39420 | G6: =F6 -> 39420 | H6: JEA | K6: 4
A7: BPS-004153 | B7: 6850 Energy Center Drive | C7: 256468 | D7: South Grid | E7: Duval | F7: 43635 | G7: =F7 -> 43635 | H7: JEA | K7: 4
A8: BPS-004187 | B8: 7806 RAMPART RD | C8: 277052 | D8: West Grid | E8: Duval | F8: 44197 | G8: =F8 -> 44197 | H8: JEA | K8: 4
A9: BPS-004228 | B9: 10477 BRADLEY RD BOOSTER | C9: 1329 | D9: East Grid | E9: Duval | F9: 44319 | G9: =F9 -> 44319 | H9: JEA | K9: 4
A10: BPS-004296 | B10: 3742 ROBENA ROAD | C10: 315233 | D10: North Grid | E10: Duval | F10: 45078 | G10: =F10 -> 45078 | H10: JEA | K10: 4
A11: BPS-004333 | B11: 85008 ART WILSON LN | C11: 354434 | D11: Nassau Grid | E11: Nassau | F11: 45350 | G11: =F11 -> 45350 | H11: FPL | K11: 4
A12: LS-000001 | B12: 12770 1ST ST | C12: 1907 | D12: North Grid | E12: Duval | F12: 25569 | G12: =F12 -> 25569 | H12: JEA | I12: 3800.0027 | J12: 391.9503 | K12: 1
A13: LS-000002 | B13: 2580 1ST ST W | C13: 54481 | D13: North Grid | E13: Duval | F13: 18264 | G13: =F13 -> 18264 | H13: JEA | I13: 679.30483 | J13: 178.69535 | K13: 1
A14: LS-000004 | B14: 1999 30TH ST W | C14: 1983 | D14: North Grid | E14: Duval | F14: 35431 | G14: =F14 -> 35431 | H14: JEA | I14: 8305.0375 | J14: 139.41558 | K14: 1
A15: LS-000005 | B15: 94 32ND ST E | C15: 1298 | D15: North Grid | E15: Duval | F15: 34700 | G15: =F15 -> 34700 | H15: JEA | I15: 158687.74 | J15: 707.47431 | K15: 4
A16: LS-000006 | B16: 1870 41ST ST W | C16: 1804 | D16: North Grid | E16: Duval | F16: 32143 | G16: =F16 -> 32143 | H16: JEA | I16: 111175.11 | J16: 1009.4588 | K16: 3
A17: LS-000007 | B17: 1646 45TH ST W | C17: 54482 | D17: North Grid | E17: Duval | F17: 21916 | G17: =F17 -> 21916 | H17: JEA | I17: 37275.195 | J17: 416.13725 | K17: 2
A18: LS-000013 | B18: 2809 5TH ST W | C18: 1941 | D18: North Grid | E18: Duval | F18: 21186 | G18: =F18 -> 21186 | H18: JEA | K18: 4
A19: LS-000014 | B19: 5233 5TH ST W | C19: 1940 | D19: West Grid | E19: Duval | F19: 19725 | G19: =F19 -> 19725 | H19: JEA | K19: 4
A20: LS-000017 | B20: 239 68TH ST W | C20: 1534 | D20: North Grid | E20: Duval | F20: 29221 | G20: =F20 -> 29221 | H20: JEA | I20: 4148.0654 | J20: 161.84871 | K20: 1
A21: LS-000018 | B21: 7200 AC SKINNER PY | C21: 1710 | D21: South Grid | E21: Duval | F21: 30317 | G21: =F21 -> 30317 | H21: JEA | K21: 4
A22: LS-000019 | B22: 5640 101ST ST | C22: 1252 | D22: West Grid | E22: Duval | F22: 18264 | G22: =F22 -> 18264 | H22: JEA | I22: 24964.525 | J22: 87.938139 | K22: 1
A23: LS-000023 | B23: MAGNOLIA VALLEY DR. 5097 | C23: 85617 | D23: West Grid | E23: Duval | F23: 40162 | G23: =F23 -> 40162 | H23: JEA | I23: 8526.1175 | J23: 334.90585 | K23: 1
A24: LS-000026 | B24: 6650 103RD ST | C24: 26881 | D24: West Grid | E24: Duval | F24: 32927 | G24: =F24 -> 32927 | H24: JEA | I24: 5872.579 | J24: 164.91228 | K24: 1
A25: LS-000033 | B25: 7960 103RD ST | C25: 1286 | D25: West Grid | E25: Duval | F25: 31778 | G25: =F25 -> 31778 | H25: JEA | I25: 13355.874 | J25: 116.98851 | K25: 1
A26: LS-000034 | B26: 9380 103RD ST | C26: 1656 | D26: West Grid | E26: Duval | F26: 36892 | G26: =F26 -> 36892 | H26: JEA | I26: 9962.3103 | J26: 58.357324 | K26: 1
A27: LS-000039 | B27: 9902 103RD ST | C27: 1655 | D27: West Grid | E27: Duval | F27: 34335 | G27: =F27 -> 34335 | H27: JEA | I27: 78098.778 | J27: 795.65975 | K27: 2
A28: LS-000045 | B28: 5104 118TH ST | C28: 1256 | D28: West Grid | E28: Duval | F28: 26299 | G28: =F28 -> 26299 | H28: JEA | K28: 4
A29: LS-000047 | B29: 5823 118TH ST | C29: 12161 | D29: West Grid | E29: Duval | F29: 37846 | G29: =F29 -> 37846 | H29: JEA | I29: 156740.52 | J29: 401.40041 | K29: 1
A30: LS-000048 | B30: 8350 118TH ST | C30: 1562 | D30: West Grid | E30: Duval | F30: 36441 | G30: =F30 -> 36441 | H30: JEA | I30: 43395.552 | J30: 250.71292 | K30: 1
A31: LS-000057 | B31: 3215 ABBEYFIELD LN | C31: 1139 | D31: East Grid | E31: Duval | F31: 29221 | G31: =F31 -> 29221 | H31: JEA | I31: 77771.083 | J31: 431.74386 | K31: 1
A32: LS-000058 | B32: 5180 ABEL LN | C32: 1490 | D32: West Grid | E32: Duval | F32: 26753 | G32: =F32 -> 26753 | H32: JEA | I32: 19641.488 | J32: 322.96819 | K32: 1
A33: LS-000060 | B33: 12733 ABESS BV | C33: 1826 | D33: East Grid | E33: Duval | F33: 31778 | G33: =F33 -> 31778 | H33: JEA | K33: 4
A34: LS-000063 | B34: 8752 ACANTHUS DR | C34: 1564 | D34: West Grid | E34: Duval | F34: 25569 | G34: =F34 -> 25569 | H34: JEA | I34: 225935.57 | J34: 445.32817 | K34: 3
A35: LS-000067 | B35: 11933 ACOSTA RD | C35: 1968 | D35: South Grid | E35: Duval | F35: 29221 | G35: =F35 -> 29221 | H35: JEA | I35: 10740.192 | J35: 359.74633 | K35: 1
A36: LS-000069 | B36: 505 ADDOR LN | C36: 1369 | D36: West Grid | E36: Duval | F36: 33813 | G36: =F36 -> 33813 | H36: JEA | I36: 1503.892 | J36: 218.86513 | K36: 1
A37: LS-000070 | B37: 9374 ADELAID DR | C37: 2241 | D37: West Grid | E37: Duval | F37: 37117 | G37: =F37 -> 37117 | H37: JEA | I37: 103743.19 | J37: 398.70769 | K37: 2
A38: LS-000071 | B38: 2844 ADELE RD | C38: 2012 | D38: South Grid | E38: Duval | F38: 29221 | G38: =F38 -> 29221 | H38: JEA | I38: 11032.907 | J38: 33.82726 | K38: 1
A39: LS-000073 | B39: 13650 AEROSPACE WAY | C39: 89458 | D39: West Grid | E39: Duval | F39: 31048 | G39: =F39 -> 31048 | H39: JEA | I39: 595.60672 | J39: 74.420632 | K39: 1
A40: LS-000074 | B40: 125 AFTON LN | C40: 1963 | D40: St Johns Grid | E40: Duval | F40: 36039 | G40: =F40 -> 36039 | H40: JEA | I40: 32722.459 | J40: 163.58411 | K40: 1
A41: LS-000075 | B41: 10150 AGAVE RD | C41: 1631 | D41: East Grid | E41: Duval | F41: 29221 | G41: =F41 -> 29221 | H41: JEA | I41: 406259.59 | J41: 2302.9151 | K41: 2
A42: LS-000076 | B42: 10398 AGAVE RD | C42: 1741 | D42: East Grid | E42: Duval | F42: 25569 | G42: =F42 -> 25569 | H42: JEA | I42: 18848.392 | J42: 123.21237 | K42: 1
A43: LS-000080 | B43: AIRPORT STATION A RAMP | C43: 29846 | D43: North Grid | E43: Duval | F43: 39029 | G43: =F43 -> 39029 | H43: JEA | I43: 22977.769 | J43: 74.822793 | K43: 2
A44: LS-000081 | B44: 7039 ALACHUA AV | C44: 1986 | D44: West Grid | E44: Duval | F44: 29587 | G44: =F44 -> 29587 | H44: JEA | K44: 4
A45: LS-000082 | B45: 11823 ALDEN RD | C45: 1344 | D45: East Grid | E45: Duval | F45: 39213 | G45: =F45 -> 39213 | H45: JEA | I45: 63990.031 | J45: 163.13396 | K45: 1
A46: LS-000083 | B46: 12106 ALDEN RD | C46: 1158 | D46: East Grid | E46: Duval | F46: 25569 | G46: =F46 -> 25569 | H46: JEA | I46: 12852.067 | J46: 362.40797 | K46: 1
A47: LS-000085 | B47: 12193 ALEXANDRA DR | C47: 19856 | D47: North Grid | E47: Duval | F47: 38512 | G47: =F47 -> 38512 | H47: JEA | I47: 48355.364 | J47: 188.21249 | K47: 1
A48: LS-000086 | B48: 11551 ALEXIS FOREST DR | C48: 1624 | D48: South Grid | E48: Duval | F48: 32874 | G48: =F48 -> 32874 | H48: JEA | I48: 38929.068 | J48: 221.70676 | K48: 1
A49: LS-000088 | B49: 907 ALIZON ST | C49: 28897 | D49: St Johns Grid | E49: Duval | F49: 36639 | G49: =F49 -> 36639 | H49: JEA | I49: 37631.494 | J49: 473.13707 | K49: 2
A50: LS-000091 | B50: 11524 ALTA DR | C50: 2881 | D50: North Grid | E50: Duval | F50: 37099 | G50: =F50 -> 37099 | H50: JEA | I50: 50874.111 | J50: 538.95213 | K50: 1
A51: LS-000097 | B51: 11009 ALUMNI WY | C51: 2034 | D51: South Grid | E51: Duval | F51: 29221 | G51: =F51 -> 29221 | H51: JEA | I51: 67197.977 | J51: 518.48566 | K51: 1
A52: LS-000098 | B52: 11220 ALUMNI WY | C52: 1069 | D52: South Grid | E52: Duval | F52: 29221 | G52: =F52 -> 29221 | H52: JEA | I52: 208112.52 | J52: 527.65605 | K52: 2
A53: LS-000099 | B53: 4172 Eco Rd | C53: 30660 | D53: East Grid | E53: Duval | F53: 38373 | G53: =F53 -> 38373 | H53: JEA | I53: 107447.05 | J53: 1318.9282 | K53: 4
A54: LS-000100 | B54: 85111 Amaryllis Ct | C54: 48721 | D54: Nassau Grid | E54: Nassau | F54: 39323 | G54: =F54 -> 39323 | H54: FPL | I54: 72641.362 | J54: 715.34595 | K54: 2
A55: LS-000103 | B55: 95352 AMELIA CONCOURSE | C55: 52257 | D55: Nassau Grid | E55: Nassau | F55: 38568 | G55: =F55 -> 38568 | H55: FPL | I55: 20375.001 | J55: 275.95753 | K55: 2
A56: LS-000104 | B56: 4172 ANDERSON WOODS DR | C56: 21776 | D56: North Grid | E56: Duval | F56: 38686 | G56: =F56 -> 38686 | H56: JEA | I56: 11835.085 | J56: 132.30658 | K56: 1
... A60: LS-000112 | B60: 12026 ARBOR LAKE DR | C60: 31297 | D60: East Grid | E60: Duval | F60: 30855 | G60: =F60 -> 30855 | H60: JEA | I60: 31454.357 | J60: 231.96668 | K60: 1
A61: LS-000113 | B61: 1092 ARBOR LN | C61: 54487 | D61: East Grid | E61: Duval | F61: 38411 | G61: =F61 -> 38411 | H61: JEA | K61: 1
A62: LS-000114 | B62: 9420 ARBOR OAK LN | C62: 72173 | D62: North Grid | E62: Duval | F62: 38580 | G62: =F62 -> 38580 | H62: JEA | I62: 52904.968 | J62: 451.21186 | K62: 2
A63: LS-000116 | B63: 6491 ARGYLE FOREST BV | C63: 1118 | D63: West Grid | E63: Duval | F63: 29221 | G63: =F63 -> 29221 | H63: JEA | I63: 139898.2 | J63: 729.92798 | K63: 2
A64: LS-000118 | B64: 7663 ARGYLE FOREST BV | C64: 1792 | D64: West Grid | E64: Duval | F64: 32143 | G64: =F64 -> 32143 | H64: JEA | I64: 266416.03 | J64: 1935.9738 | K64: 2
A65: LS-000119 | B65: 8104 ARGYLE FOREST BV | C65: 1514 | D65: West Grid | E65: Duval | F65: 25569 | G65: =F65 -> 25569 | H65: JEA | K65: 4
A66: LS-000120 | B66: 9526 ARGYLE FOREST BV | C66: 41697 | D66: West Grid | E66: Duval | F66: 37901 | G66: =F66 -> 37901 | H66: JEA | I66: 24544.808 | J66: 354.6924 | K66: 1
A67: LS-000122 | B67: 6912 ARLEX DR S | C67: 27953 | D67: East Grid | E67: Duval | F67: 21438 | G67: =F67 -> 21438 | H67: JEA | I67: 3695.6994 | J67: 21.893738 | K67: 1
A68: LS-000123 | B68: 1090 ARLINGTON RD | C68: 39090 | D68: East Grid | E68: Duval | F68: 28374 | G68: =F68 -> 28374 | H68: JEA | I68: 17401.622 | J68: 90.266297 | K68: 1
A69: LS-000130 | B69: 6233 ARLINGTON XWAY | C69: 36881 | D69: East Grid | E69: Duval | F69: 26151 | G69: =F69 -> 26151 | H69: JEA | I69: 2634.5869 | J69: 129.54166 | K69: 1
A70: LS-000132 | B70: 7528 ARLINGTON XY | C70: 39121 | D70: East Grid | E70: Duval | F70: 32751 | G70: =F70 -> 32751 | H70: JEA | I70: 29977.029 | J70: 126.99117 | K70: 1
A71: LS-000133 | B71: 7837 ARLINGTON XY | C71: 34817 | D71: East Grid | E71: Duval | F71: 24777 | G71: =F71 -> 24777 | H71: JEA | I71: 27566.208 | J71: 180.30731 | K71: 1
A72: LS-000134 | B72: 8052 ARLINGTON XY | C72: 36785 | D72: East Grid | E72: Duval | F72: 26402 | G72: =F72 -> 26402 | H72: JEA | I72: 34833.425 | J72: 166.26334 | K72: 2
A73: LS-000138 | B73: 3194 ARMSDALE RD | C73: 8004 | D73: North Grid | E73: Duval | F73: 37518 | G73: =F73 -> 37518 | H73: JEA | I73: 880.53989 | J73: 42.319762 | K73: 1
A74: LS-000140 | B74: 6661 ARROWROOT DR | C74: 1793 | D74: West Grid | E74: Duval | F74: 25569 | G74: =F74 -> 25569 | H74: JEA | I74: 12047.36 | J74: 19.781583 | K74: 1
A75: LS-000147 | B75: 9099 ARUNDELL WY | C75: 1182 | D75: South Grid | E75: Duval | F75: 29221 | G75: =F75 -> 29221 | H75: JEA | I75: 44612.025 | J75: 277.21518 | K75: 2
A76: LS-000148 | B76: 10031 ASHFORD CROSSING | C76: 1191 | D76: South Grid | E76: Duval | F76: 29221 | G76: =F76 -> 29221 | H76: JEA | I76: 5633.5912 | J76: 292.73034 | K76: 1
A77: LS-000149 | B77: 4894 ASHLEY MANOR WY | C77: 14731 | D77: East Grid | E77: Duval | F77: 32806 | G77: =F77 -> 32806 | H77: JEA | I77: 31573.354 | J77: 278.34293 | K77: 1
... A91: LS-000229 | B91: 4501 BARKOSKIE RD | C91: 1445 | D91: South Grid | E91: Duval | F91: 31048 | G91: =F91 -> 31048 | H91: JEA | I91: 4409.5128 | J91: 159.02897 | K91: 1
A92: LS-000230 | B92: 4437 BARNES RD | C92: 1901 | D92: East Grid | E92: Duval | F92: 37950 | G92: =F92 -> 37950 | H92: JEA | K92: 3
A93: LS-000231 | B93: 2158 BARNSTORMER RD AIRPORT STA. B | C93: 52946 | D93: North Grid | E93: Duval | F93: 35065 | G93: =F93 -> 35065 | H93: JEA | I93: 15688.098 | J93: 65.614515 | K93: 2
A94: LS-000233 | B94: 6039 BARTOLF AV | C94: 1557 | D94: West Grid | E94: Duval | F94: 18264 | G94: =F94 -> 18264 | H94: JEA | I94: 1446.7472 | J94: 36.716842 | K94: 1
A95: LS-000235 | B95: 12882 BARTRAM PARK BV | C95: 14085 | D95: St Johns Grid | E95: Duval | F95: 38037 | G95: =F95 -> 38037 | H95: JEA | K95: 3
A96: LS-000236 | B96: 13551 BARTRAM PARK BV | C96: 72134 | D96: St Johns Grid | E96: Duval | F96: 38832 | G96: =F96 -> 38832 | H96: JEA | I96: 49675.146 | J96: 693.73632 | K96: 1
A97: LS-000237 | B97: 14041 BARTRAM PARK BV | C97: 72108 | D97: St Johns Grid | E97: Duval | F97: 39091 | G97: =F97 -> 39091 | H97: JEA | K97: 4
A98: LS-000241 | B98: 6046 BARTRAM VILLAGE DR | C98: 54491 | D98: St Johns Grid | E98: Duval | F98: 38950 | G98: =F98 -> 38950 | H98: JEA | I98: 32117.676 | J98: 243.42063 | K98: 1
A99: LS-000243 | B99: 6263 BATTLE GATE RD | C99: 30537 | D99: South Grid | E99: Duval | F99: 38540 | G99: =F99 -> 38540 | H99: JEA | I99: 80111.227 | J99: 605.56965 | K99: 2
A100: LS-000244 | B100: 4568 BAY HARBOUR DR | C100: 14732 | D100: East Grid | E100: Duval | F100: 31373 | G100: =F100 -> 31373 | H100: JEA | K100: 3
A101: LS-000245 | B101: 4 BAY ST E | C101: 54492 | D101: North Grid | E101: Duval | F101: 37911 | G101: =F101 -> 37911 | H101: JEA | I101: 1879.9985 | J101: 96.347903 | K101: 1
A102: LS-000246 | B102: 834 BAY ST E | C102: 1902 | D102: North Grid | E102: Duval | F102: 24108 | G102: =F102 -> 24108 | H102: JEA | K102: 4
A103: LS-000247 | B103: 7999 BAYBERRY RD | C103: 17601 | D103: South Grid | E103: Duval | F103: 27485 | G103: =F103 -> 27485 | H103: JEA | I103: 11898.455 | J103: 134.52954 | K103: 1
A104: LS-000248 | B104: 5239 BAYCREST RD | C104: 1373 | D104: West Grid | E104: Duval | F104: 25934 | G104: =F104 -> 25934 | H104: JEA | I104: 16794.041 | J104: 372.90578 | K104: 1
A105: LS-000249 | B105: 8751 BAYLEAF DR | C105: 17282 | D105: South Grid | E105: Duval | F105: 26257 | G105: =F105 -> 26257 | H105: JEA | I105: 136111.73 | J105: 242.35823 | K105: 3
A106: LS-000250 | B106: 7640 BAYMEADOWS CR W | C106: 16646 | D106: South Grid | E106: Duval | F106: 30748 | G106: =F106 -> 30748 | H106: JEA | I106: 32943.937 | J106: 136.39798 | K106: 1
A107: LS-000251 | B107: 7836 BAYMEADOWS CR W | C107: 16652 | D107: South Grid | E107: Duval | F107: 26746 | G107: =F107 -> 26746 | H107: JEA | I107: 20506.234 | J107: 141.42432 | K107: 1
A108: LS-000254 | B108: 10702 BAYMEADOWS RD | C108: 1193 | D108: South Grid | E108: Duval | F108: 29221 | G108: =F108 -> 29221 | H108: JEA | I108: 284942.37 | J108: 826.43697 | K108: 3
A109: LS-000255 | B109: 3847 BAYMEADOWS RD | C109: 15375 | D109: South Grid | E109: Duval | F109: 26046 | G109: =F109 -> 26046 | H109: JEA | I109: 3607.3923 | J109: 124.63667 | K109: 1
A110: LS-000256 | B110: 8115 BAYMEADOWS CR W | C110: 382844 | D110: South Grid | E110: Duval | F110: 45600 | G110: =F110 -> 45600 | H110: JEA | I110: 67404.139 | J110: 174.31238 | K110: 3
A111: LS-000258 | B111: 7823 BAYMEADOWS RD E | C111: 1614 | D111: South Grid | E111: Duval | F111: 36972 | G111: =F111 -> 36972 | H111: JEA | I111: 141393.62 | J111: 671.65015 | K111: 2
A112: LS-000259 | B112: 8036 BAYMEADOWS RD E | C112: 11845 | D112: South Grid | E112: Duval | F112: 37812 | G112: =F112 -> 37812 | H112: JEA | I112: 290755.53 | J112: 1508.6849 | K112: 3
A113: LS-000260 | B113: 7160 BAYMEADOWS WY | C113: 2010 | D113: South Grid | E113: Duval | F113: 36416 | G113: =F113 -> 36416 | H113: JEA | I113: 24135.041 | J113: 408.88083 | K113: 2
A114: LS-000261 | B114: 8800 BAYMEADOWS WY | C114: 18886 | D114: South Grid | E114: Duval | F114: 29575 | G114: =F114 -> 29575 | H114: JEA | I114: 16039.207 | J114: 89.572075 | K114: 1
A115: LS-000262 | B115: 7611 BAYMEADOWS WY W | C115: 15693 | D115: South Grid | E115: Duval | F115: 29929 | G115: =F115 -> 29929 | H115: JEA | I115: 8918.4684 | J115: 129.04331 | K115: 1
A116: LS-000263 | B116: 9733 BAYOU BLUFF DR | C116: 2017 | D116: South Grid | E116: Duval | F116: 31048 | G116: =F116 -> 31048 | H116: JEA | K116: 3
...

Sheet car_edit
A1: Asset ID | B1: Location Address | C1: JEA GIS Object ID | D1: Sewer Maintenance District | E1: County | F1: Best Estimate of Install Date of Station | G1: Year of Install | H1: Electrical Supplier | I1: JEA Actual ADF (GPD) | J1: JEA Design PHF (GPM) | K1: PS Class
A2: BPS-000639 | B2: 2740 CR 210 | C2: 205269 | D2: St Johns Grid | E2: St Johns | F2: 42676 | G2: =F2 -> 42676 | H2: JEA | I2: 2861084.5 | J2: 7000
A3: BPS-001645 | B3: 4193 OLDFIELD CROSSING | C3: 1729 | D3: South Grid | E3: Duval | F3: 42755 | G3: =F3 -> 42755 | H3: JEA | I3: 2714538.5 | J3: 9370
A4: BPS-001950 | B4: 4241 SAN CLERC | C4: 16966 | D4: South Grid | E4: Duval | F4: 41143 | G4: =F4 -> 41143 | H4: JEA | I4: 932000 | J4: 3040
A5: BPS-002867 | B5: 8617 WESTERN WAY | C5: 204646 | D5: South Grid | E5: Duval | F5: 38533 | G5: =F5 -> 38533 | H5: JEA | I5: 2827540.5 | J5: 5000
A6: BPS-003387 | B6: 106 TWIN CREEKS Dr | C6: 55153 | D6: St Johns Grid | E6: Duval | F6: 39420 | G6: =F6 -> 39420 | H6: JEA | I6: 2481327.6 | J6: 4400
A7: BPS-004153 | B7: 6850 Energy Center Drive | C7: 256468 | D7: South Grid | E7: Duval | F7: 43635 | G7: =F7 -> 43635 | H7: JEA | I7: 166464 | J7: 1200
A8: BPS-004187 | B8: 7806 RAMPART RD | C8: 277052 | D8: West Grid | E8: Duval | F8: 44197 | G8: =F8 -> 44197 | H8: JEA | I8: 2297937.6 | J8: 5000
A9: BPS-004228 | B9: 10477 BRADLEY RD BOOSTER | C9: 1329 | D9: East Grid | E9: Duval | F9: 44319 | G9: =F9 -> 44319 | H9: JEA | I9: 12497059 | J9: 19500
A10: BPS-004296 | B10: 3742 ROBENA ROAD | C10: 315233 | D10: North Grid | E10: Duval | F10: 45078 | G10: =F10 -> 45078 | H10: JEA
A11: BPS-004333 | B11: 85008 ART WILSON LN | C11: 354434 | D11: Nassau Grid | E11: Nassau | F11: 45350 | G11: =F11 -> 45350 | H11: FPL
A12: LS-000001 | B12: 12770 1ST ST | C12: 1907 | D12: North Grid | E12: Duval | F12: 25569 | G12: =F12 -> 25569 | H12: JEA
A13: LS-000002 | B13: 2580 1ST ST W | C13: 54481 | D13: North Grid | E13: Duval | F13: 18264 | G13: =F13 -> 18264 | H13: JEA
A14: LS-000004 | B14: 1999 30TH ST W | C14: 1983 | D14: North Grid | E14: Duval | F14: 35431 | G14: =F14 -> 35431 | H14: JEA
A15: LS-000005 | B15: 94 32ND ST E | C15: 1298 | D15: North Grid | E15: Duval | F15: 34700 | G15: =F15 -> 34700 | H15: JEA | I15: 1014995.5 | J15: 2500
A16: LS-000006 | B16: 1870 41ST ST W | C16: 1804 | D16: North Grid | E16: Duval | F16: 32143 | G16: =F16 -> 32143 | H16: JEA | I16: 94847.049 | J16: 1500
A17: LS-000007 | B17: 1646 45TH ST W | C17: 54482 | D17: North Grid | E17: Duval | F17: 21916 | G17: =F17 -> 21916 | H17: JEA
A18: LS-000013 | B18: 2809 5TH ST W | C18: 1941 | D18: North Grid | E18: Duval | F18: 21186 | G18: =F18 -> 21186 | H18: JEA | I18: 1852554.1 | J18: 10000
A19: LS-000014 | B19: 5233 5TH ST W | C19: 1940 | D19: West Grid | E19: Duval | F19: 19725 | G19: =F19 -> 19725 | H19: JEA | I19: 510479.35 | J19: 1250
A20: LS-000017 | B20: 239 68TH ST W | C20: 1534 | D20: North Grid | E20: Duval | F20: 29221 | G20: =F20 -> 29221 | H20: JEA
A21: LS-000018 | B21: 7200 AC SKINNER PY | C21: 1710 | D21: South Grid | E21: Duval | F21: 30317 | G21: =F21 -> 30317 | H21: JEA | I21: 1224444.4 | J21: 3770
A22: LS-000019 | B22: 5640 101ST ST | C22: 1252 | D22: West Grid | E22: Duval | F22: 18264 | G22: =F22 -> 18264 | H22: JEA
A23: LS-000023 | B23: MAGNOLIA VALLEY DR. 5097 | C23: 85617 | D23: West Grid | E23: Duval | F23: 40162 | G23: =F23 -> 40162 | H23: JEA
A24: LS-000026 | B24: 6650 103RD ST | C24: 26881 | D24: West Grid | E24: Duval | F24: 32927 | G24: =F24 -> 32927 | H24: JEA
A25: LS-000033 | B25: 7960 103RD ST | C25: 1286 | D25: West Grid | E25: Duval | F25: 31778 | G25: =F25 -> 31778 | H25: JEA
A26: LS-000034 | B26: 9380 103RD ST | C26: 1656 | D26: West Grid | E26: Duval | F26: 36892 | G26: =F26 -> 36892 | H26: JEA
A27: LS-000039 | B27: 9902 103RD ST | C27: 1655 | D27: West Grid | E27: Duval | F27: 34335 | G27: =F27 -> 34335 | H27: JEA
A28: LS-000045 | B28: 5104 118TH ST | C28: 1256 | D28: West Grid | E28: Duval | F28: 26299 | G28: =F28 -> 26299 | H28: JEA | I28: 3940176 | J28: 15000
A29: LS-000047 | B29: 5823 118TH ST | C29: 12161 | D29: West Grid | E29: Duval | F29: 37846 | G29: =F29 -> 37846 | H29: JEA
A30: LS-000048 | B30: 8350 118TH ST | C30: 1562 | D30: West Grid | E30: Duval | F30: 36441 | G30: =F30 -> 36441 | H30: JEA
A31: LS-000057 | B31: 3215 ABBEYFIELD LN | C31: 1139 | D31: East Grid | E31: Duval | F31: 29221 | G31: =F31 -> 29221 | H31: JEA
A32: LS-000058 | B32: 5180 ABEL LN | C32: 1490 | D32: West Grid | E32: Duval | F32: 26753 | G32: =F32 -> 26753 | H32: JEA
A33: LS-000060 | B33: 12733 ABESS BV | C33: 1826 | D33: East Grid | E33: Duval | F33: 31778 | G33: =F33 -> 31778 | H33: JEA | I33: 2713621.3 | J33: 8000
A34: LS-000063 | B34: 8752 ACANTHUS DR | C34: 1564 | D34: West Grid | E34: Duval | F34: 25569 | G34: =F34 -> 25569 | H34: JEA | I34: 264041.89 | J34: 800
A35: LS-000067 | B35: 11933 ACOSTA RD | C35: 1968 | D35: South Grid | E35: Duval | F35: 29221 | G35: =F35 -> 29221 | H35: JEA
A36: LS-000069 | B36: 505 ADDOR LN | C36: 1369 | D36: West Grid | E36: Duval | F36: 33813 | G36: =F36 -> 33813 | H36: JEA
A37: LS-000070 | B37: 9374 ADELAID DR | C37: 2241 | D37: West Grid | E37: Duval | F37: 37117 | G37: =F37 -> 37117 | H37: JEA
A38: LS-000071 | B38: 2844 ADELE RD | C38: 2012 | D38: South Grid | E38: Duval | F38: 29221 | G38: =F38 -> 29221 | H38: JEA
A39: LS-000073 | B39: 13650 AEROSPACE WAY | C39: 89458 | D39: West Grid | E39: Duval | F39: 31048 | G39: =F39 -> 31048 | H39: JEA
A40: LS-000074 | B40: 125 AFTON LN | C40: 1963 | D40: St Johns Grid | E40: Duval | F40: 36039 | G40: =F40 -> 36039 | H40: JEA
A41: LS-000075 | B41: 10150 AGAVE RD | C41: 1631 | D41: East Grid | E41: Duval | F41: 29221 | G41: =F41 -> 29221 | H41: JEA
A42: LS-000076 | B42: 10398 AGAVE RD | C42: 1741 | D42: East Grid | E42: Duval | F42: 25569 | G42: =F42 -> 25569 | H42: JEA
A43: LS-000080 | B43: AIRPORT STATION A RAMP | C43: 29846 | D43: North Grid | E43: Duval | F43: 39029 | G43: =F43 -> 39029 | H43: JEA
A44: LS-000081 | B44: 7039 ALACHUA AV | C44: 1986 | D44: West Grid | E44: Duval | F44: 29587 | G44: =F44 -> 29587 | H44: JEA | I44: 1799391.2 | J44: 6500
A45: LS-000082 | B45: 11823 ALDEN RD | C45: 1344 | D45: East Grid | E45: Duval | F45: 39213 | G45: =F45 -> 39213 | H45: JEA
A46: LS-000083 | B46: 12106 ALDEN RD | C46: 1158 | D46: East Grid | E46: Duval | F46: 25569 | G46: =F46 -> 25569 | H46: JEA
A47: LS-000085 | B47: 12193 ALEXANDRA DR | C47: 19856 | D47: North Grid | E47: Duval | F47: 38512 | G47: =F47 -> 38512 | H47: JEA
A48: LS-000086 | B48: 11551 ALEXIS FOREST DR | C48: 1624 | D48: South Grid | E48: Duval | F48: 32874 | G48: =F48 -> 32874 | H48: JEA
A49: LS-000088 | B49: 907 ALIZON ST | C49: 28897 | D49: St Johns Grid | E49: Duval | F49: 36639 | G49: =F49 -> 36639 | H49: JEA
A50: LS-000091 | B50: 11524 ALTA DR | C50: 2881 | D50: North Grid | E50: Duval | F50: 37099 | G50: =F50 -> 37099 | H50: JEA
A51: LS-000097 | B51: 11009 ALUMNI WY | C51: 2034 | D51: South Grid | E51: Duval | F51: 29221 | G51: =F51 -> 29221 | H51: JEA
A52: LS-000098 | B52: 11220 ALUMNI WY | C52: 1069 | D52: South Grid | E52: Duval | F52: 29221 | G52: =F52 -> 29221 | H52: JEA | I52: 170800 | J52: 533.66602
A53: LS-000099 | B53: 4172 Eco Rd | C53: 30660 | D53: East Grid | E53: Duval | F53: 38373 | G53: =F53 -> 38373 | H53: JEA | I53: 23000 | J53: 1700
A54: LS-000100 | B54: 85111 Amaryllis Ct | C54: 48721 | D54: Nassau Grid | E54: Nassau | F54: 39323 | G54: =F54 -> 39323 | H54: FPL
A55: LS-000103 | B55: 95352 AMELIA CONCOURSE | C55: 52257 | D55: Nassau Grid | E55: Nassau | F55: 38568 | G55: =F55 -> 38568 | H55: FPL
A56: LS-000104 | B56: 4172 ANDERSON WOODS DR | C56: 21776 | D56: North Grid | E56: Duval | F56: 38686 | G56: =F56 -> 38686 | H56: JEA
A57: LS-000109 | B57: 10922 APPLE BLOSSOM TL E | C57: 11844 | D57: North Grid | E57: Duval | F57: 37985 | G57: =F57 -> 37985 | H57: JEA
A58: LS-000110 | B58: 8825 ARBOR BREEZE LN | C58: 52944 | D58: West Grid | E58: Duval | F58: 39114 | G58: =F58 -> 39114 | H58: JEA
A59: LS-000111 | B59: 11867 ARBOR LAKE DR | C59: 31330 | D59: East Grid | E59: Duval | F59: 30947 | G59: =F59 -> 30947 | H59: JEA
A60: LS-000112 | B60: 12026 ARBOR LAKE DR | C60: 31297 | D60: East Grid | E60: Duval | F60: 30855 | G60: =F60 -> 30855 | H60: JEA
A61: LS-000113 | B61: 1092 ARBOR LN | C61: 54487 | D61: East Grid | E61: Duval | F61: 38411 | G61: =F61 -> 38411 | H61: JEA
A62: LS-000114 | B62: 9420 ARBOR OAK LN | C62: 72173 | D62: North Grid | E62: Duval | F62: 38580 | G62: =F62 -> 38580 | H62: JEA
A63: LS-000116 | B63: 6491 ARGYLE FOREST BV | C63: 1118 | D63: West Grid | E63: Duval | F63: 29221 | G63: =F63 -> 29221 | H63: JEA
A64: LS-000118 | B64: 7663 ARGYLE FOREST BV | C64: 1792 | D64: West Grid | E64: Duval | F64: 32143 | G64: =F64 -> 32143 | H64: JEA
A65: LS-000119 | B65: 8104 ARGYLE FOREST BV | C65: 1514 | D65: West Grid | E65: Duval | F65: 25569 | G65: =F65 -> 25569 | H65: JEA | I65: 114000 | J65: 800
A66: LS-000120 | B66: 9526 ARGYLE FOREST BV | C66: 41697 | D66: West Grid | E66: Duval | F66: 37901 | G66: =F66 -> 37901 | H66: JEA
A67: LS-000122 | B67: 6912 ARLEX DR S | C67: 27953 | D67: East Grid | E67: Duval | F67: 21438 | G67: =F67 -> 21438 | H67: JEA
A68: LS-000123 | B68: 1090 ARLINGTON RD | C68: 39090 | D68: East Grid | E68: Duval | F68: 28374 | G68: =F68 -> 28374 | H68: JEA
A69: LS-000130 | B69: 6233 ARLINGTON XWAY | C69: 36881 | D69: East Grid | E69: Duval | F69: 26151 | G69: =F69 -> 26151 | H69: JEA
A70: LS-000132 | B70: 7528 ARLINGTON XY | C70: 39121 | D70: East Grid | E70: Duval | F70: 32751 | G70: =F70 -> 32751 | H70: JEA
A71: LS-000133 | B71: 7837 ARLINGTON XY | C71: 34817 | D71: East Grid | E71: Duval | F71: 24777 | G71: =F71 -> 24777 | H71: JEA
A72: LS-000134 | B72: 8052 ARLINGTON XY | C72: 36785 | D72: East Grid | E72: Duval | F72: 26402 | G72: =F72 -> 26402 | H72: JEA
A73: LS-000138 | B73: 3194 ARMSDALE RD | C73: 8004 | D73: North Grid | E73: Duval | F73: 37518 | G73: =F73 -> 37518 | H73: JEA
A74: LS-000140 | B74: 6661 ARROWROOT DR | C74: 1793 | D74: West Grid | E74: Duval | F74: 25569 | G74: =F74 -> 25569 | H74: JEA
A75: LS-000147 | B75: 9099 ARUNDELL WY | C75: 1182 | D75: South Grid | E75: Duval | F75: 29221 | G75: =F75 -> 29221 | H75: JEA
A76: LS-000148 | B76: 10031 ASHFORD CROSSING | C76: 1191 | D76: South Grid | E76: Duval | F76: 29221 | G76: =F76 -> 29221 | H76: JEA
A77: LS-000149 | B77: 4894 ASHLEY MANOR WY | C77: 14731 | D77: East Grid | E77: Duval | F77: 32806 | G77: =F77 -> 32806 | H77: JEA
... A91: LS-000229 | B91: 4501 BARKOSKIE RD | C91: 1445 | D91: South Grid | E91: Duval | F91: 31048 | G91: =F91 -> 31048 | H91: JEA
A92: LS-000230 | B92: 4437 BARNES RD | C92: 1901 | D92: East Grid | E92: Duval | F92: 37950 | G92: =F92 -> 37950 | H92: JEA | I92: 652418.36 | J92: 2000
A93: LS-000231 | B93: 2158 BARNSTORMER RD AIRPORT STA. B | C93: 52946 | D93: North Grid | E93: Duval | F93: 35065 | G93: =F93 -> 35065 | H93: JEA
A94: LS-000233 | B94: 6039 BARTOLF AV | C94: 1557 | D94: West Grid | E94: Duval | F94: 18264 | G94: =F94 -> 18264 | H94: JEA
A95: LS-000235 | B95: 12882 BARTRAM PARK BV | C95: 14085 | D95: St Johns Grid | E95: Duval | F95: 38037 | G95: =F95 -> 38037 | H95: JEA | I95: 352236.29 | J95: 2120
A96: LS-000236 | B96: 13551 BARTRAM PARK BV | C96: 72134 | D96: St Johns Grid | E96: Duval | F96: 38832 | G96: =F96 -> 38832 | H96: JEA
A97: LS-000237 | B97: 14041 BARTRAM PARK BV | C97: 72108 | D97: St Johns Grid | E97: Duval | F97: 39091 | G97: =F97 -> 39091 | H97: JEA | I97: 103000 | J97: 1040
A98: LS-000241 | B98: 6046 BARTRAM VILLAGE DR | C98: 54491 | D98: St Johns Grid | E98: Duval | F98: 38950 | G98: =F98 -> 38950 | H98: JEA
A99: LS-000243 | B99: 6263 BATTLE GATE RD | C99: 30537 | D99: South Grid | E99: Duval | F99: 38540 | G99: =F99 -> 38540 | H99: JEA
A100: LS-000244 | B100: 4568 BAY HARBOUR DR | C100: 14732 | D100: East Grid | E100: Duval | F100: 31373 | G100: =F100 -> 31373 | H100: JEA | I100: 585015.31 | J100: 2400
A101: LS-000245 | B101: 4 BAY ST E | C101: 54492 | D101: North Grid | E101: Duval | F101: 37911 | G101: =F101 -> 37911 | H101: JEA
A102: LS-000246 | B102: 834 BAY ST E | C102: 1902 | D102: North Grid | E102: Duval | F102: 24108 | G102: =F102 -> 24108 | H102: JEA | I102: 3443586.1 | J102: 19250
A103: LS-000247 | B103: 7999 BAYBERRY RD | C103: 17601 | D103: South Grid | E103: Duval | F103: 27485 | G103: =F103 -> 27485 | H103: JEA
A104: LS-000248 | B104: 5239 BAYCREST RD | C104: 1373 | D104: West Grid | E104: Duval | F104: 25934 | G104: =F104 -> 25934 | H104: JEA
A105: LS-000249 | B105: 8751 BAYLEAF DR | C105: 17282 | D105: South Grid | E105: Duval | F105: 26257 | G105: =F105 -> 26257 | H105: JEA | I105: 300837.9 | J105: 800
A106: LS-000250 | B106: 7640 BAYMEADOWS CR W | C106: 16646 | D106: South Grid | E106: Duval | F106: 30748 | G106: =F106 -> 30748 | H106: JEA
A107: LS-000251 | B107: 7836 BAYMEADOWS CR W | C107: 16652 | D107: South Grid | E107: Duval | F107: 26746 | G107: =F107 -> 26746 | H107: JEA
A108: LS-000254 | B108: 10702 BAYMEADOWS RD | C108: 1193 | D108: South Grid | E108: Duval | F108: 29221 | G108: =F108 -> 29221 | H108: JEA | I108: 357750.32 | J108: 900
A109: LS-000255 | B109: 3847 BAYMEADOWS RD | C109: 15375 | D109: South Grid | E109: Duval | F109: 26046 | G109: =F109 -> 26046 | H109: JEA
A110: LS-000256 | B110: 8115 BAYMEADOWS CR W | C110: 382844 | D110: South Grid | E110: Duval | F110: 45600 | G110: =F110 -> 45600 | H110: JEA | I110: 359664.75 | J110: 700
A111: LS-000258 | B111: 7823 BAYMEADOWS RD E | C111: 1614 | D111: South Grid | E111: Duval | F111: 36972 | G111: =F111 -> 36972 | H111: JEA
A112: LS-000259 | B112: 8036 BAYMEADOWS RD E | C112: 11845 | D112: South Grid | E112: Duval | F112: 37812 | G112: =F112 -> 37812 | H112: JEA | I112: 312798.53 | J112: 1458.6934
A113: LS-000260 | B113: 7160 BAYMEADOWS WY | C113: 2010 | D113: South Grid | E113: Duval | F113: 36416 | G113: =F113 -> 36416 | H113: JEA
...

Sheet reference-->

Sheet Major_CAR
B1: Asset | F1: Capacity Analysis | M1: 10-Year Forecast | S1: Projects | V1: Resiliency
A2: Basin | B2: CMMS | C2: Liftstation | D2: Class | F2: ADF | H2: PHF | I2: Capacity | K2: Utilization | M2: Growth | O2: ADF | P2: PHF | Q2: Utilization | S2: Related | T2: In-Service | V2: Num Pumps | W2: Station Bypass | X2: VFD Control | Y2: Pressure Gauge | Z2: Flow Meter
F3: (kGPD) | H3: (GPM) | I3: (GPM) | K3: (%) | M3: (%) | O3: (kGPD) | P3: (GPM) | Q3: (%)
A4: ARLINGTON EAST | B4: LS-001093 | C4: HOLIDAY RD S - 7834 | D4: 4 | F4: 1484.5624 | G4: 1 | H4: 2868.8733 | I4: 2800 | J4: 2 | K4: 1.0245976 | M4: 0.023739267 | N4: 1 | O4: =F4*(1+M4)^10 -> 1877.1202 | P4: =(18+SQRT(O4/100))/(4+SQRT(O4/100))*O4*1000/1440 -> 3493.7287 | Q4: =P4/I4 -> 1.2477602 | S4: 180-70 | T4: 2024 | V4: 3 | W4: 2 | X4: 1 | Y4: 1 | Z4: 0
A5: ARLINGTON EAST | B5: LS-000256 | C5: BAYMEADOWS RD - 9247 | D5: 3 | F5: 359.66475 | G5: 1 | H5: 842.7886 | I5: 700 | J5: 2 | K5: 1.2039837 | M5: 0.018404212 | N5: 1 | O5: =F5*(1+M5)^10 -> 431.61819 | P5: =(18+SQRT(O5/100))/(4+SQRT(O5/100))*O5*1000/1440 -> 990.19291 | Q5: =P5/I5 -> 1.4145613 | S5: 180-53 | T5: 2025 | V5: 2 | W5: 1 | X5: 0 | Y5: 1 | Z5: 0
A6: ARLINGTON EAST | B6: LS-000249 | C6: BAYLEAF RD - 8751 | D6: 3 | F6: 300.8379 | G6: 1 | H6: 718.95606 | I6: 800 | J6: 2 | K6: 0.89869508 | M6: 0.0056539838 | N6: 1 | O6: =F6*(1+M6)^10 -> 318.28658 | P6: =(18+SQRT(O6/100))/(4+SQRT(O6/100))*O6*1000/1440 -> 756.02914 | Q6: =P6/I6 -> 0.94503642 | S6: 180-54 | T6: 2026 | V6: 2 | W6: 1 | X6: 1 | Y6: 1 | Z6: 0
A7: ARLINGTON EAST | B7: LS-000495 | C7: BURNT MILL RD - 10828 | D7: 4 | F7: 1816.5661 | G7: 1 | H7: 3399.0986 | I7: 3100 | J7: 2 | K7: 1.0964834 | M7: 0.027202133 | N7: 1 | O7: =F7*(1+M7)^10 -> 2375.8025 | P7: =(18+SQRT(O7/100))/(4+SQRT(O7/100))*O7*1000/1440 -> 4252.692 | Q7: =P7/I7 -> 1.3718361 | S7: 175-66 | T7: 2028 | V7: 3 | W7: 1 | X7: 1 | Y7: 1 | Z7: 0
A8: ARLINGTON EAST | B8: LS-001813 | C8: PRINCETON SQUARE BV W - 8331 | D8: 3 | F8: 604.55655 | G8: 1 | H8: 1329.8541 | I8: 900 | J8: 2 | K8: 1.4776157 | M8: 0.00055848368 | N8: 1 | O8: =F8*(1+M8)^10 -> 607.9414 | P8: =(18+SQRT(O8/100))/(4+SQRT(O8/100))*O8*1000/1440 -> 1336.3269 | Q8: =P8/I8 -> 1.4848077 | S8: 180-57 | T8: 2028 | V8: 2 | W8: 1 | X8: 0 | Y8: 1 | Z8: 0
A9: ARLINGTON EAST | B9: LS-000018 | C9: A C SKINNER PY - 7200 | D9: 4 | F9: 1224.4444 | G9: 1 | H9: 2437.7194 | I9: 3770 | J9: 2 | K9: 0.64660993 | M9: 0.027669931 | N9: 1 | O9: =F9*(1+M9)^10 -> 1608.7019 | P9: =(18+SQRT(O9/100))/(4+SQRT(O9/100))*O9*1000/1440 -> 3069.5228 | Q9: =P9/I9 -> 0.81419703 | V9: 4 | W9: 2 | X9: 1 | Y9: 0 | Z9: 0
A10: ARLINGTON EAST | B10: LS-000060 | C10: ABESS BV - 12733 | D10: 4 | F10: 2713.6213 | G10: 4 | H10: 4749.2364 | I10: 8000 | J10: 2 | K10: 0.59365455 | M10: 0.01311607 | N10: 1 | O10: =F10*(1+M10)^10 -> 3091.3009 | P10: =(18+SQRT(O10/100))/(4+SQRT(O10/100))*O10*1000/1440 -> 5290.5109 | Q10: =P10/I10 -> 0.66131387 | V10: 4 | W10: 2 | X10: 0 | Y10: 1 | Z10: 1
A11: ARLINGTON EAST | B11: LS-000098 | C11: ALUMNI WY - 11220 | D11: 3 | F11: 170.8 | G11: 2 | H11: 431.51583 | I11: 533.66602 | J11: 1 | K11: 0.8085878 | M11: 0.0032458029 | N11: 1 | O11: =F11*(1+M11)^10 -> 176.42551 | P11: =(18+SQRT(O11/100))/(4+SQRT(O11/100))*O11*1000/1440 -> 444.43338 | Q11: =P11/I11 -> 0.8327931 | V11: 2 | W11: 1 | X11: 0 | Y11: 0 | Z11: 0
A12: ARLINGTON EAST | B12: LS-003974 | C12: BALBOA RD - 7106 | D12: 3 | F12: 268.01287 | G12: 1 | H12: 648.35704 | I12: 1360 | J12: 2 | K12: 0.47673311 | M12: 0.00042099215 | N12: 1 | O12: =F12*(1+M12)^10 -> 269.14332 | P12: =(18+SQRT(O12/100))/(4+SQRT(O12/100))*O12*1000/1440 -> 650.80792 | Q12: =P12/I12 -> 0.47853523 | V12: 3 | W12: 2 | X12: 0 | Y12: 1 | Z12: 0
A13: ARLINGTON EAST | B13: LS-000244 | C13: BAY HARBOUR DR - 4568 | D13: 3 | F13: 585.01531 | G13: 1 | H13: 1292.3654 | I13: 2400 | J13: 2 | K13: 0.5384856 | M13: 0.0019950733 | N13: 1 | O13: =F13*(1+M13)^10 -> 596.79214 | P13: =(18+SQRT(O13/100))/(4+SQRT(O13/100))*O13*1000/1440 -> 1314.9832 | Q13: =P13/I13 -> 0.54790965 | V13: 3 | W13: 1 | X13: 0 | Y13: 1 | Z13: 0
A14: ARLINGTON EAST | B14: LS-000254 | C14: BAYMEADOWS RD - 10702 | D14: 3 | F14: 357.75032 | G14: 1 | H14: 838.80861 | I14: 900 | J14: 2 | K14: 0.93200957 | M14: 0 | N14: 2 | O14: =F14*(1+M14)^10 -> 357.75032 | P14: =(18+SQRT(O14/100))/(4+SQRT(O14/100))*O14*1000/1440 -> 838.80861 | Q14: =P14/I14 -> 0.93200957 | V14: 2 | W14: 1 | X14: 0 | Y14: 1 | Z14: 0
A15: ARLINGTON EAST | B15: LS-000259 | C15: BAYMEADOWS RD E - 8036 | D15: 3 | F15: 312.79853 | G15: 1 | H15: 744.40127 | I15: 1458.6934 | J15: 1 | K15: 0.51032059 | M15: 0.036535777 | N15: 1 | O15: =F15*(1+M15)^10 -> 447.82432 | P15: =(18+SQRT(O15/100))/(4+SQRT(O15/100))*O15*1000/1440 -> 1022.8457 | Q15: =P15/I15 -> 0.70120681 | V15: 2 | W15: 1 | X15: 0 | Y15: 1 | Z15: 0
A16: ARLINGTON EAST | B16: LS-000370 | C16: BELFORT OAKS PL - 6868 | D16: 3 | F16: 233 | G16: 3 | H16: 571.70421 | I16: 1000 | J16: 2 | K16: 0.57170421 | M16: 0.039501976 | N16: 1 | O16: =F16*(1+M16)^10 -> 343.24887 | P16: =(18+SQRT(O16/100))/(4+SQRT(O16/100))*O16*1000/1440 -> 808.55592 | Q16: =P16/I16 -> 0.80855592 | V16: 2 | W16: 1 | X16: 0 | Y16: 1 | Z16: 0
A17: ARLINGTON EAST | B17: LS-000451 | C17: BOWLAN ST N - 544 | D17: 4 | F17: 295.08814 | G17: 1 | H17: 706.67229 | I17: 1200 | J17: 2 | K17: 0.58889357 | M17: 0.02252212 | N17: 1 | O17: =F17*(1+M17)^10 -> 368.70487 | P17: =(18+SQRT(O17/100))/(4+SQRT(O17/100))*O17*1000/1440 -> 861.53971 | Q17: =P17/I17 -> 0.71794976 | V17: 4 | W17: 1 | X17: 1 | Y17: 1 | Z17: 0
A18: ARLINGTON EAST | B18: BPS-004228 | C18: BRADLEY RD - 10477 | D18: 4 | F18: 12497.059 | G18: 1 | H18: 16682.926 | I18: 19500 | J18: 2 | K18: 0.85553467 | M18: 0.0085762833 | N18: 4 | O18: =F18*(1+M18)^10 -> 13611.166 | P18: =(18+SQRT(O18/100))/(4+SQRT(O18/100))*O18*1000/1440 -> 17898.831 | Q18: =P18/I18 -> 0.91788878 | V18: 6 | W18: 2 | X18: 1 | Y18: 1 | Z18: 0
A19: ARLINGTON EAST | B19: LS-000536 | C19: CEDAR ISLAND DR - 14600 | D19: 3 | F19: 269.68929 | G19: 1 | H19: 651.99108 | I19: 1130 | J19: 2 | K19: 0.57698326 | M19: 0.0062091023 | N19: 1 | O19: =F19*(1+M19)^10 -> 286.91029 | P19: =(18+SQRT(O19/100))/(4+SQRT(O19/100))*O19*1000/1440 -> 689.14186 | Q19: =P19/I19 -> 0.60986005 | V19: 2 | W19: 1 | X19: 1 | Y19: 1 | Z19: 0
A20: ARLINGTON EAST | B20: LS-000540 | C20: CENTRAL PY - 11550 | D20: 3 | F20: 199.869 | G20: 1 | H20: 497.7304 | I20: 1026.6982 | J20: 1 | K20: 0.48478746 | M20: 0.0062275976 | N20: 1 | O20: =F20*(1+M20)^10 -> 212.67071 | P20: =(18+SQRT(O20/100))/(4+SQRT(O20/100))*O20*1000/1440 -> 526.49148 | Q20: =P20/I20 -> 0.51280064 | V20: 2 | W20: 1 | X20: 0 | Y20: 0 | Z20: 0
... A26: ARLINGTON EAST | B26: LS-001187 | C26: FIRST COAST TECH PY - 5192 | D26: 3 | F26: 71.811324 | G26: 2 | H26: 193.8974 | I26: 497.69927 | J26: 1 | K26: 0.38958748 | M26: 0.05 | N26: 2 | O26: =F26*(1+M26)^10 -> 116.97308 | P26: =(18+SQRT(O26/100))/(4+SQRT(O26/100))*O26*1000/1440 -> 305.02922 | Q26: =P26/I26 -> 0.61287858 | V26: 2 | W26: 1 | X26: 0 | Y26: 1 | Z26: 0
A27: ARLINGTON EAST | B27: LS-000915 | C27: FT CAROLINE RD - 10797 | D27: 3 | F27: 1259 | G27: 3 | H27: 2495.9126 | I27: 2500 | J27: 2 | K27: 0.99836505 | M27: 0.002035898 | N27: 1 | O27: =F27*(1+M27)^10 -> 1284.8681 | P27: =(18+SQRT(O27/100))/(4+SQRT(O27/100))*O27*1000/1440 -> 2539.2816 | Q27: =P27/I27 -> 1.0157127 | S27: * | V27: 2 | W27: 2 | X27: 0 | Y27: 1 | Z27: 0
A28: ARLINGTON EAST | B28: LS-000932 | C28: GATE PY N - 9898 | D28: 4 | F28: 487.7684 | G28: 1 | H28: 1102.5448 | I28: 2000 | J28: 3 | K28: 0.55127239 | M28: 0.012877142 | N28: 1 | O28: =F28*(1+M28)^10 -> 554.34657 | P28: =(18+SQRT(O28/100))/(4+SQRT(O28/100))*O28*1000/1440 -> 1233.1047 | Q28: =P28/I28 -> 0.61655237 | V28: 3 | W28: 1 | X28: 1 | Y28: 1 | Z28: 0
A29: ARLINGTON EAST | B29: LS-000956 | C29: GLEN KERN PY - 12858 | D29: 3 | F29: 119.43772 | G29: 1 | H29: 310.94765 | I29: 1200 | J29: 2 | K29: 0.25912304 | M29: 0.032279624 | N29: 3 | O29: =F29*(1+M29)^10 -> 164.10245 | P29: =(18+SQRT(O29/100))/(4+SQRT(O29/100))*O29*1000/1440 -> 416.06815 | Q29: =P29/I29 -> 0.34672346 | V29: 2 | W29: 1 | X29: 0 | Y29: 1 | Z29: 0
A30: ARLINGTON EAST | B30: LS-000997 | C30: GROVE PARK BV - 487 | D30: 3 | F30: 423.22649 | G30: 1 | H30: 973.20962 | I30: 1400 | J30: 3 | K30: 0.69514973 | M30: 0.034387391 | N30: 1 | O30: =F30*(1+M30)^10 -> 593.47854 | P30: =(18+SQRT(O30/100))/(4+SQRT(O30/100))*O30*1000/1440 -> 1308.6269 | Q30: =P30/I30 -> 0.93473351 | V30: 2 | W30: 2 | X30: 0 | Y30: 1 | Z30: 0
A31: ARLINGTON EAST | B31: LS-001089 | C31: HODGES BV - 1705 | D31: 4 | F31: 948.16813 | G31: 1 | H31: 1960.6109 | I31: 3200 | J31: 2 | K31: 0.61269092 | M31: 0.0043491527 | N31: 1 | O31: =F31*(1+M31)^10 -> 990.2219 | P31: =(18+SQRT(O31/100))/(4+SQRT(O31/100))*O31*1000/1440 -> 2034.7165 | Q31: =P31/I31 -> 0.6358489 | V31: 2 | W31: 2 | X31: 0 | Y31: 1 | Z31: 0
A32: ARLINGTON EAST | B32: LS-001114 | C32: HUFFMAN BV - 2798 | D32: 4 | F32: 3465.9897 | G32: 1 | H32: 5815.0709 | I32: 7000 | J32: 2 | K32: =H32/I32 -> 0.83072441 | M32: 0.021296507 | N32: 1 | O32: =F32*(1+M32)^10 -> 4279.034 | P32: =(18+SQRT(O32/100))/(4+SQRT(O32/100))*O32*1000/1440 -> 6918.0472 | Q32: =P32/I32 -> 0.98829245 | S32: * | V32: 3 | W32: 2 | X32: 1 | Y32: 1 | Z32: 0
A33: ARLINGTON EAST | B33: LS-001185 | C33: KERN BV S - 3431 | D33: 3 | F33: 263 | G33: 3 | H33: 637.4714 | I33: 1547.9593 | J33: 1 | K33: 0.41181405 | M33: 0.014887645 | N33: 1 | O33: =F33*(1+M33)^10 -> 304.88454 | P33: =(18+SQRT(O33/100))/(4+SQRT(O33/100))*O33*1000/1440 -> 727.58103 | Q33: =P33/I33 -> 0.47002594 | V33: 2 | W33: 1 | X33: 0 | Y33: 1 | Z33: 0
A34: ARLINGTON EAST | B34: LS-001207 | C34: LA VISTA CR - 4181 | D34: 3 | F34: 231.68027 | G34: 2 | H34: 568.78557 | I34: 1048.3784 | J34: 1 | K34: 0.54253843 | M34: 0.00015895064 | N34: 1 | O34: =F34*(1+M34)^10 -> 232.0488 | P34: =(18+SQRT(O34/100))/(4+SQRT(O34/100))*O34*1000/1440 -> 569.6008 | Q34: =P34/I34 -> 0.54331604 | V34: 2 | W34: 1 | X34: 0 | Y34: 1 | Z34: 0
A35: ARLINGTON EAST | B35: LS-001459 | C35: MILL CREEK RD - 1030 | D35: 3 | F35: 184.3553 | G35: 1 | H35: 462.55577 | I35: 1490 | J35: 2 | K35: 0.31044011 | M35: 0.066357065 | N35: 1 | O35: =F35*(1+M35)^10 -> 350.49525 | P35: =(18+SQRT(O35/100))/(4+SQRT(O35/100))*O35*1000/1440 -> 823.69658 | Q35: =P35/I35 -> 0.5528165 | V35: 3 | W35: 1 | X35: 0 | Y35: 1 | Z35: 0
A36: ARLINGTON EAST | B36: LS-001851 | C36: REEDY BRANCH DR - 8614 | D36: 4 | F36: 40.660666 | G36: 2 | H36: 113.47617 | I36: 2221.0143 | J36: 1 | K36: 0.051092049 | M36: 0 | N36: 3 | O36: =F36*(1+M36)^10 -> 40.660666 | P36: =(18+SQRT(O36/100))/(4+SQRT(O36/100))*O36*1000/1440 -> 113.47617 | Q36: =P36/I36 -> 0.051092049 | V36: 2 | W36: 1 | X36: 0 | Y36: 1 | Z36: 0
A37: ARLINGTON EAST | B37: LS-001933 | C37: RYAR RD - 1531 | D37: 4 | F37: 382.72639 | G37: 1 | H37: 890.48654 | I37: 1750 | J37: 2 | K37: 0.50884945 | M37: 0.043661692 | N37: 1 | O37: =F37*(1+M37)^10 -> 586.79423 | P37: =(18+SQRT(O37/100))/(4+SQRT(O37/100))*O37*1000/1440 -> 1295.7867 | Q37: =P37/I37 -> 0.74044956 | V37: 3 | W37: 1 | X37: 0 | Y37: 0 | Z37: 0
A38: ARLINGTON EAST | B38: BPS-001950 | C38: SAN CLERC RD - 4241 | D38: 4 | F38: 932 | G38: 3 | H38: 1931.9637 | I38: 3040 | J38: 2 | K38: 0.63551436 | M38: 0.002894213 | N38: 3 | O38: =F38*(1+M38)^10 -> 959.3281 | P38: =(18+SQRT(O38/100))/(4+SQRT(O38/100))*O38*1000/1440 -> 1980.3333 | Q38: =P38/I38 -> 0.65142544 | V38: 3 | W38: 1 | X38: 1 | Y38: 1 | Z38: 0
A39: ARLINGTON EAST | B39: LS-002007 | C39: SAN PABLO RD S - 4950 | D39: 3 | F39: 62.38835 | G39: 2 | H39: 169.95797 | I39: 1061 | J39: 2 | K39: 0.16018659 | M39: 0.013307063 | N39: 1 | O39: =F39*(1+M39)^10 -> 71.205608 | P39: =(18+SQRT(O39/100))/(4+SQRT(O39/100))*O39*1000/1440 -> 192.36751 | Q39: =P39/I39 -> 0.18130773 | V39: 2 | W39: 1 | X39: 0 | Y39: 1 | Z39: 0
A40: ARLINGTON EAST | B40: LS-002104 | C40: SOUTHSIDE BV - 7133 | D40: 4 | F40: 1037.9629 | G40: 1 | H40: 2118.1579 | I40: 3150 | J40: 3 | K40: 0.67243109 | M40: 0.03 | N40: 2 | O40: =F40*(1+M40)^10 -> 1394.9353 | P40: =(18+SQRT(O40/100))/(4+SQRT(O40/100))*O40*1000/1440 -> 2722.0439 | Q40: =P40/I40 -> 0.86414091 | V40: 3 | W40: 2 | X40: 1 | Y40: 1 | Z40: 0
A41: ARLINGTON EAST | B41: LS-002112 | C41: SOUTHSIDE BV - 9041 | D41: 3 | F41: 320.53673 | G41: 1 | H41: 760.78818 | I41: 900 | J41: 2 | K41: 0.84532021 | M41: 0.0082285439 | N41: 1 | O41: =F41*(1+M41)^10 -> 347.91062 | P41: =(18+SQRT(O41/100))/(4+SQRT(O41/100))*O41*1000/1440 -> 818.30164 | Q41: =P41/I41 -> 0.90922404 | V41: 3 | W41: 1 | X41: 0 | Y41: 1 | Z41: 0
A42: ARLINGTON EAST | B42: LS-002243 | C42: SUTTON PARK DR N - 13825 | D42: 3 | F42: 696.15003 | G42: 1 | H42: 1502.9691 | I42: 1700 | J42: 3 | K42: 0.88409948 | M42: 0.0028394635 | N42: 1 | O42: =F42*(1+M42)^10 -> 716.17145 | P42: =(18+SQRT(O42/100))/(4+SQRT(O42/100))*O42*1000/1440 -> 1540.2763 | Q42: =P42/I42 -> 0.90604488 | V42: 3 | W42: 1 | X42: 0 | Y42: 0 | Z42: 0
A43: ARLINGTON EAST | B43: LS-002289 | C43: TOUCHTON RD - 8362 | D43: 3 | F43: 166.79392 | G43: 2 | H43: 422.28503 | I43: 2375.2079 | J43: 1 | K43: 0.17778866 | M43: 0.0062432867 | N43: 1 | O43: =F43*(1+M43)^10 -> 177.50483 | P43: =(18+SQRT(O43/100))/(4+SQRT(O43/100))*O43*1000/1440 -> 446.9059 | Q43: =P43/I43 -> 0.18815443 | V43: 2 | W43: 1 | X43: 0 | Y43: 1 | Z43: 0
A44: ARLINGTON EAST | B44: LS-002294 | C44: TOWN CENTER PY - 4522 | D44: 4 | F44: 462.27551 | G44: 1 | H44: 1051.8055 | I44: 1500 | J44: 2 | K44: =H44/I44 -> 0.70120364 | M44: 0.040527624 | N44: 1 | O44: =F44*(1+M44)^10 -> 687.76019 | P44: =(18+SQRT(O44/100))/(4+SQRT(O44/100))*O44*1000/1440 -> 1487.2811 | Q44: =P44/I44 -> 0.99152077 | S44: * | V44: 3 | W44: 1 | X44: 0 | Y44: 1 | Z44: 0
A45: ARLINGTON EAST | B45: LS-002307 | C45: TRESCA RD - 420 | D45: 3 | F45: 403.02978 | G45: 1 | H45: 932.11747 | I45: 1930 | J45: 2 | K45: 0.48296242 | M45: 0.00072549187 | N45: 1 | O45: =F45*(1+M45)^10 -> 405.96329 | P45: =(18+SQRT(O45/100))/(4+SQRT(O45/100))*O45*1000/1440 -> 938.10545 | Q45: =P45/I45 -> 0.486065 | V45: 2 | W45: 1 | X45: 0 | Y45: 1 | Z45: 0
A46: ARLINGTON EAST | B46: LS-002308 | C46: TROPIC EGRET DR - 13383 | D46: 4 | F46: 544.16175 | G46: 1 | H46: 1213.306 | I46: 2560 | J46: 2 | K46: 0.47394767 | M46: 0.0092713376 | N46: 1 | O46: =F46*(1+M46)^10 -> 596.77059 | P46: =(18+SQRT(O46/100))/(4+SQRT(O46/100))*O46*1000/1440 -> 1314.9418 | Q46: =P46/I46 -> 0.51364916 | V46: 3 | W46: 2 | X46: 0 | Y46: 1 | Z46: 0
A47: ARLINGTON EAST | B47: LS-002410 | C47: WESTERN LAKE DR - 8652 | D47: 3 | F47: 79.5 | G47: 2 | H47: 213.2 | I47: 721.52367 | J47: 1 | K47: 0.2954858 | M47: 0.01 | N47: 2 | O47: =F47*(1+M47)^10 -> 87.817459 | P47: =(18+SQRT(O47/100))/(4+SQRT(O47/100))*O47*1000/1440 -> 233.91566 | Q47: =P47/I47 -> 0.32419679 | V47: 2 | W47: 1 | X47: 0 | Y47: 0 | Z47: 0
A48: ARLINGTON EAST | B48: BPS-002867 | C48: WESTERN WY - 8617 | D48: 4 | F48: 2827.5405 | G48: 4 | H48: 4913.9415 | I48: 5000 | J48: 2 | K48: 0.98278831 | M48: 0.0047771568 | N48: 1 | O48: =F48*(1+M48)^10 -> 2965.5576 | P48: =(18+SQRT(O48/100))/(4+SQRT(O48/100))*O48*1000/1440 -> 5111.7913 | Q48: =P48/I48 -> 1.0223583 | S48: * | V48: 4 | W48: 1 | X48: 1 | Y48: 1 | Z48: 1
A49: BLACKS FORD | B49: BPS-000639 | C49: COUNTY ROAD 210 W - 2740 | D49: 4 | F49: 2861.0845 | G49: 4 | H49: 4962.1948 | I49: 7000 | J49: 2 | K49: 0.70888496 | M49: 0.053983789 | N49: 4 | O49: =F49*(1+M49)^10 -> 4840.2745 | P49: =(18+SQRT(O49/100))/(4+SQRT(O49/100))*O49*1000/1440 -> 7656.0294 | Q49: =P49/I49 -> 1.0937185 | S49: 180-56 | T49: 2026 | V49: 3 | W49: 2 | X49: 1 | Y49: 1 | Z49: 1
A50: BLACKS FORD | B50: BPS-003387 | C50: TWIN CREEKS RD - 106 | D50: 4 | F50: 2481.3276 | G50: 1 | H50: 4409.1738 | I50: 4400 | J50: 2 | K50: 1.002085 | M50: 0.062523724 | N50: 1 | O50: =F50*(1+M50)^10 -> 4550.6189 | P50: =(18+SQRT(O50/100))/(4+SQRT(O50/100))*O50*1000/1440 -> 7277.2968 | Q50: =P50/I50 -> 1.6539311 | S50: 180-56 | T50: 2026 | V50: 2 | W50: 2 | X50: 1 | Y50: 1 | Z50: 0
A51: BLACKS FORD | B51: LS-004088 | C51: CROSSWATER LAKE DR - 245 | D51: 3 | F51: 228.05537 | G51: 1 | H51: 560.75736 | I51: 970 | J51: 2 | K51: 0.57810037 | M51: 0.05 | N51: 2 | O51: =F51*(1+M51)^10 -> 371.47817 | P51: =(18+SQRT(O51/100))/(4+SQRT(O51/100))*O51*1000/1440 -> 867.27813 | Q51: =P51/I51 -> 0.89410116 | V51: 3 | W51: 1 | X51: 1 | Y51: 1 | Z51: 0
A52: BLACKS FORD | B52: LS-002812 | C52: HAWKCREST DR E - 2369 | D52: 3 | F52: 251.69113 | G52: 1 | H52: 612.80697 | I52: 1500 | J52: 2 | K52: 0.40853798 | M52: 0.000145507 | N52: 1 | O52: =F52*(1+M52)^10 -> 252.0576 | P52: =(18+SQRT(O52/100))/(4+SQRT(O52/100))*O52*1000/1440 -> 613.60859 | Q52: =P52/I52 -> 0.40907239 | V52: 3 | W52: 1 | X52: 0 | Y52: 1 | Z52: 0
A53: BLACKS FORD | B53: LS-001139 | C53: ISLESBROOK PY - 112 | D53: 3 | F53: 243.85941 | G53: 2 | H53: 595.63699 | I53: 1241.0038 | J53: 1 | K53: 0.47996387 | M53: 0.0074360482 | N53: 1 | O53: =F53*(1+M53)^10 -> 262.61189 | P53: =(18+SQRT(O53/100))/(4+SQRT(O53/100))*O53*1000/1440 -> 636.62742 | Q53: =P53/I53 -> 0.51299392 | V53: 2 | W53: 1 | X53: 0 | Y53: 0 | Z53: 0
A54: BLACKS FORD | B54: LS-003612 | C54: NOCATEE VILLAGE DR - 79 | D54: 3 | F54: 108.14677 | G54: 1 | H54: 283.72101 | I54: 1324 | J54: 2 | K54: 0.21429079 | M54: 0.086520406 | N54: 1 | O54: =F54*(1+M54)^10 -> 247.96617 | P54: =(18+SQRT(O54/100))/(4+SQRT(O54/100))*O54*1000/1440 -> 604.64974 | Q54: =P54/I54 -> 0.4566841 | V54: 3 | W54: 1 | X54: 0 | Y54: 1 | Z54: 0
A55: BLACKS FORD | B55: LS-004285 | C55: PEYTON PY E - 155 | D55: 3 | F55: 3.2688 | G55: 4 | H55: 9.8714192 | I55: 617.15966 | J55: 1 | K55: 0.01599492 | M55: 0.1 | N55: 2 | O55: =F55*(1+M55)^10 -> 8.4784254 | P55: =(18+SQRT(O55/100))/(4+SQRT(O55/100))*O55*1000/1440 -> 25.096774 | Q55: =P55/I55 -> 0.040664962 | V55: 2 | W55: 2 | X55: 0 | Y55: 0 | Z55: 1
A56: BLACKS FORD | B56: LS-001887 | C56: RIVER RUN BV - 1018 | D56: 3 | F56: 165.60206 | G56: 1 | H56: 419.53354 | I56: 1140 | J56: 2 | K56: 0.36801188 | M56: 0.056194471 | N56: 1 | O56: =F56*(1+M56)^10 -> 286.09129 | P56: =(18+SQRT(O56/100))/(4+SQRT(O56/100))*O56*1000/1440 -> 687.38232 | Q56: =P56/I56 -> 0.60296695 | V56: 3 | W56: 1 | X56: 1 | Y56: 0 | Z56: 0
A57: BLACKS FORD | B57: LS-004046 | C57: SHERWATER PY - 635 | D57: 3 | F57: 242.23178 | G57: 1 | H57: 592.05925 | I57: 1600 | J57: 2 | K57: 0.37003703 | M57: 0.03 | N57: 2 | O57: =F57*(1+M57)^10 -> 325.53926 | P57: =(18+SQRT(O57/100))/(4+SQRT(O57/100))*O57*1000/1440 -> 771.35105 | Q57: =P57/I57 -> 0.4820944 | V57: 2 | W57: 1 | X57: 1 | Y57: 0 | Z57: 0
A58: BLACKS FORD | B58: LS-002186 | C58: ST JOHNS PY - 2084 | D58: 3 | F58: 96 | G58: 3 | H58: 254.09068 | I58: 1485.0567 | J58: 1 | K58: 0.1710983 | M58: 0.11552519 | N58: 1 | O58: =F58*(1+M58)^10 -> 286.46071 | P58: =(18+SQRT(O58/100))/(4+SQRT(O58/100))*O58*1000/1440 -> 688.17608 | Q58: =P58/I58 -> 0.46340054 | V58: 2 | W58: 1 | X58: 0 | Y58: 1 | Z58: 0
A59: BUCKMAN | B59: LS-000014 | C59: 5TH ST W - 5233 | D59: 4 | F59: 510.47935 | G59: 1 | H59: 1147.3887 | I59: 1250 | J59: 2 | K59: 0.91791096 | M59: 0.086086814 | N59: 1 | O59: =F59*(1+M59)^10 -> 1165.7988 | P59: =(18+SQRT(O59/100))/(4+SQRT(O59/100))*O59*1000/1440 -> 2338.2545 | Q59: =P59/I59 -> 1.8706036 | S59: 100-40 | T59: 2024 | V59: 3 | W59: 1 | X59: 0 | Y59: 1 | Z59: 0
A60: BUCKMAN | B60: LS-002416 | C60: PRITCHARD RD - 7615 | D60: 3 | F60: 426.18148 | G60: 1 | H60: 979.19594 | I60: 1600 | J60: 2 | K60: 0.61199746 | M60: 0.084830141 | N60: 3 | O60: =F60*(1+M60)^10 -> 962.08182 | P60: =(18+SQRT(O60/100))/(4+SQRT(O60/100))*O60*1000/1440 -> 1985.1935 | Q60: =P60/I60 -> 1.2407459 | S60: 100-40 | T60: 2024 | V60: 3 | W60: 2 | X60: 0 | Y60: 0 | Z60: 0
A61: BUCKMAN | B61: LS-002131 | C61: SPRING PARK RD - 4511 | D61: 4 | F61: 1462.2752 | G61: 1 | H61: 2832.5212 | I61: 6000 | J61: 2 | K61: 0.47208687 | M61: 0.012329321 | N61: 1 | O61: =F61*(1+M61)^10 -> 1652.9026 | P61: =(18+SQRT(O61/100))/(4+SQRT(O61/100))*O61*1000/1440 -> 3140.2496 | Q61: =P61/I61 -> 0.52337493 | S61: 180-23 | T61: 2025 | V61: 2 | W61: 1 | X61: 0 | Y61: 0 | Z61: 0
A62: BUCKMAN | B62: LS-002252 | C62: TALLEYRAND AV - 1636 | D62: 4 | F62: 8275.8713 | G62: 1 | H62: 11890.429 | I62: 46000 | J62: 2 | K62: 0.25848758 | M62: 0.032128238 | N62: 1 | O62: =F62*(1+M62)^10 -> 11354.038 | P62: =(18+SQRT(O62/100))/(4+SQRT(O62/100))*O62*1000/1440 -> 15416.817 | Q62: =P62/I62 -> 0.3351482 | S62: 180-36 | T62: 2028 | V62: 3 | W62: 0 | X62: 1 | Y62: 0 | Z62: 0
A63: BUCKMAN | B63: LS-000005 | C63: 32ND ST E - 94 | D63: 4 | F63: 1014.9955 | G63: 1 | H63: 2078.1046 | I63: 2500 | J63: 2 | K63: =H63/I63 -> 0.83124182 | M63: 0.020475743 | N63: 1 | O63: =F63*(1+M63)^10 -> 1243.0568 | P63: =(18+SQRT(O63/100))/(4+SQRT(O63/100))*O63*1000/1440 -> 2469.1008 | Q63: =P63/I63 -> 0.98764032 | S63: * | V63: 2 | W63: 1 | X63: 0 | Y63: 1 | Z63: 0
A64: BUCKMAN | B64: LS-000006 | C64: 41ST ST W - 1870 | D64: 3 | F64: 94.847049 | G64: 2 | H64: 251.25878 | I64: 1500 | J64: 2 | K64: 0.16750585 | M64: 0.014801199 | N64: 3 | O64: =F64*(1+M64)^10 -> 109.85847 | P64: =(18+SQRT(O64/100))/(4+SQRT(O64/100))*O64*1000/1440 -> 287.86749 | Q64: =P64/I64 -> 0.19191166 | V64: 2 | W64: 1 | X64: 0 | Y64: 0 | Z64: 0
A65: BUCKMAN | B65: LS-000013 | C65: 5TH ST W - 2809 | D65: 4 | F65: 1852.5541 | G65: 1 | H65: 3455.4096 | I65: 10000 | J65: 2 | K65: 0.34554096 | M65: 0.073170038 | N65: 1 | O65: =F65*(1+M65)^10 -> 3753.6718 | P65: =(18+SQRT(O65/100))/(4+SQRT(O65/100))*O65*1000/1440 -> 6210.4526 | Q65: =P65/I65 -> 0.62104526 | V65: 4 | W65: 2 | X65: 1 | Y65: 0 | Z65: 0
A66: BUCKMAN | B66: LS-000230 | C66: BARNES RD - 4437 | D66: 3 | F66: 652.41836 | G66: 1 | H66: 1420.8309 | I66: 2000 | J66: 2 | K66: 0.71041546 | M66: 0.014491238 | N66: 1 | O66: =F66*(1+M66)^10 -> 753.37149 | P66: =(18+SQRT(O66/100))/(4+SQRT(O66/100))*O66*1000/1440 -> 1609.1204 | Q66: =P66/I66 -> 0.8045602 | V66: 3 | W66: 2 | X66: 0 | Y66: 1 | Z66: 0
A67: BUCKMAN | B67: LS-000246 | C67: BAY ST E - 834 | D67: 4 | F67: 3443.5861 | G67: 1 | H67: 5784.0227 | I67: 19250 | J67: 2 | K67: 0.30046871 | M67: 0.033043762 | N67: 1 | O67: =F67*(1+M67)^10 -> 4766.484 | P67: =(18+SQRT(O67/100))/(4+SQRT(O67/100))*O67*1000/1440 -> 7559.9605 | Q67: =P67/I67 -> 0.39272522 | V67: 4 | W67: 0 | X67: 1 | Y67: 1 | Z67: 0
A68: BUCKMAN | B68: LS-000365 | C68: BEAVER ST W - 9801 | D68: 3 | F68: 140 | G68: 3 | H68: 359.82195 | I68: 928.66749 | J68: 1 | K68: 0.38746048 | M68: 0.019469487 | N68: 3 | O68: =F68*(1+M68)^10 -> 169.77368 | P68: =(18+SQRT(O68/100))/(4+SQRT(O68/100))*O68*1000/1440 -> 429.15353 | Q68: =P68/I68 -> 0.46211753 | V68: 2 | W68: 1 | X68: 0 | Y68: 1 | Z68: 0
A69: BUCKMAN | B69: LS-000444 | C69: BOULEVARD - 1706 | D69: 3 | F69: 357.21904 | G69: 1 | H69: 837.70355 | I69: 1700 | J69: 2 | K69: 0.49276679 | M69: 0.01268686 | N69: 1 | O69: =F69*(1+M69)^10 -> 405.21578 | P69: =(18+SQRT(O69/100))/(4+SQRT(O69/100))*O69*1000/1440 -> 936.58023 | Q69: =P69/I69 -> 0.55092955 | V69: 2 | W69: 1 | X69: 0 | Y69: 1 | Z69: 0
A70: BUCKMAN | B70: LS-000489 | C70: BRYAN ST - 250 | D70: 3 | F70: 36.665046 | G70: 2 | H70: 102.86156 | I70: 423.39457 | J70: 1 | K70: 0.24294492 | M70: 0.01 | N70: 2 | O70: =F70*(1+M70)^10 -> 40.501021 | P70: =(18+SQRT(O70/100))/(4+SQRT(O70/100))*O70*1000/1440 -> 113.05358 | Q70: =P70/I70 -> 0.26701707 | V70: 2 | W70: 1 | X70: 0 | Y70: 0 | Z70: 0
A71: BUCKMAN | B71: LS-000824 | C71: ELLIS RD N - 1060 | D71: 3 | F71: 403.34085 | G71: 1 | H71: 932.75275 | I71: 1000 | J71: 2 | K71: 0.93275275 | M71: 0 | N71: 4 | O71: =F71*(1+M71)^10 -> 403.34085 | P71: =(18+SQRT(O71/100))/(4+SQRT(O71/100))*O71*1000/1440 -> 932.75275 | Q71: =P71/I71 -> 0.93275275 | V71: 2 | W71: 1 | X71: 0 | Y71: 1 | Z71: 0
A72: BUCKMAN | B72: LS-000491 | C72: EVERGREEN AV - 5301 | D72: 4 | F72: 532.90861 | G72: 1 | H72: 1191.3596 | I72: 8000 | J72: 2 | K72: 0.14891995 | M72: 0.020927281 | N72: 1 | O72: =F72*(1+M72)^10 -> 655.54246 | P72: =(18+SQRT(O72/100))/(4+SQRT(O72/100))*O72*1000/1440 -> 1426.7292 | Q72: =P72/I72 -> 0.17834115 | V72: 3 | W72: 1 | X72: 1 | Y72: 1 | Z72: 0
A73: BUCKMAN | B73: LS-000882 | C73: FISH RD - 10301 | D73: 3 | F73: 26 | G73: 3 | H73: 74.105062 | I73: 2000 | J73: 2 | K73: 0.037052531 | M73: 0.19979272 | N73: 1 | O73: =F73*(1+M73)^10 -> 160.70729 | P73: =(18+SQRT(O73/100))/(4+SQRT(O73/100))*O73*1000/1440 -> 408.20819 | Q73: =P73/I73 -> 0.20410409 | V73: 2 | W73: 1 | X73: 0 | Y73: 1 | Z73: 0
A74: BUCKMAN | B74: LS-001059 | C74: HERSCHEL ST - 3806 | D74: 4 | F74: 426.15107 | G74: 1 | H74: 979.13437 | I74: 3800 | J74: 2 | K74: 0.25766694 | M74: 0.009446647 | N74: 1 | O74: =F74*(1+M74)^10 -> 468.16321 | P74: =(18+SQRT(O74/100))/(4+SQRT(O74/100))*O74*1000/1440 -> 1063.5628 | Q74: =P74/I74 -> 0.27988494 | V74: 3 | W74: 1 | X74: 1 | Y74: 1 | Z74: 0
A75: BUCKMAN | B75: LS-001098 | C75: HOLLYBROOK AV - 210 | D75: 4 | F75: 2306.2282 | G75: 1 | H75: 4148.792 | I75: 11250 | J75: 2 | K75: 0.36878151 | M75: 0.011187759 | N75: 1 | O75: =F75*(1+M75)^10 -> 2577.6285 | P75: =(18+SQRT(O75/100))/(4+SQRT(O75/100))*O75*1000/1440 -> 4550.8637 | Q75: =P75/I75 -> 0.40452121 | V75: 2 | W75: 1 | X75: 0 | Y75: 1 | Z75: 0
... A87: BUCKMAN | B87: LS-002189 | C87: STANDISH PL - 718 | D87: 4 | F87: 1705.6086 | G87: 1 | H87: 3224.1192 | I87: 18500 | J87: 2 | K87: 0.17427671 | M87: 0.03058021 | N87: 1 | O87: =F87*(1+M87)^10 -> 2305.1403 | P87: =(18+SQRT(O87/100))/(4+SQRT(O87/100))*O87*1000/1440 -> 4147.1626 | Q87: =P87/I87 -> 0.22417095 | V87: 4 | W87: 0 | X87: 1 | Y87: 1 | Z87: 0
A88: BUCKMAN | B88: LS-002190 | C88: STANFORD RD - 5621 | D88: 3 | F88: 461.21198 | G88: 1 | H88: 1049.6791 | I88: 1260 | J88: 2 | K88: 0.83307867 | M88: 0.016045132 | N88: 1 | O88: =F88*(1+M88)^10 -> 540.79239 | P88: =(18+SQRT(O88/100))/(4+SQRT(O88/100))*O88*1000/1440 -> 1206.7428 | Q88: =P88/I88 -> 0.95773241 | S88: * | V88: 2 | W88: 1 | X88: 0 | Y88: 1 | Z88: 0
A89: BUCKMAN | B89: LS-002254 | C89: TALLEYRAND AV - 2446 | D89: 3 | F89: 209.19665 | G89: 1 | H89: 518.70929 | I89: 800 | J89: 3 | K89: 0.64838661 | M89: 0.0072931129 | N89: 3 | O89: =F89*(1+M89)^10 -> 224.96418 | P89: =(18+SQRT(O89/100))/(4+SQRT(O89/100))*O89*1000/1440 -> 553.89771 | Q89: =P89/I89 -> 0.69237214 | V89: 2 | W89: 0 | X89: 0 | Y89: 0 | Z89: 0
A90: BUCKMAN | B90: LS-002359 | C90: UTAH AV - 2045 | D90: 4 | F90: 3916.5883 | G90: 1 | H90: 6431.7809 | I90: 28500 | J90: 2 | K90: 0.22567652 | M90: 0.034118216 | N90: 1 | O90: =F90*(1+M90)^10 -> 5477.8458 | P90: =(18+SQRT(O90/100))/(4+SQRT(O90/100))*O90*1000/1440 -> 8475.2007 | Q90: =P90/I90 -> 0.29737546 | V90: 4 | W90: 0 | X90: 1 | Y90: 1 | Z90: 0
A91: BUCKMAN | B91: LS-002394 | C91: WATER ST - 604 | D91: 4 | F91: 437.53928 | G91: 1 | H91: 1002.145 | I91: 3500 | J91: 2 | K91: 0.28632713 | M91: 0.045271345 | N91: 1 | O91: =F91*(1+M91)^10 -> 681.25154 | P91: =(18+SQRT(O91/100))/(4+SQRT(O91/100))*O91*1000/1440 -> 1475.0882 | Q91: =P91/I91 -> 0.42145377 | V91: 2 | W91: 1 | X91: 0 | Y91: 1 | Z91: 0
A92: BUCKMAN | B92: LS-002442 | C92: WILLOW BRANCH AV - 1818 | D92: 3 | F92: 204.75654 | G92: 1 | H92: 508.73847 | I92: 940 | J92: 2 | K92: 0.54121113 | M92: 0.0091913657 | N92: 1 | O92: =F92*(1+M92)^10 -> 224.37427 | P92: =(18+SQRT(O92/100))/(4+SQRT(O92/100))*O92*1000/1440 -> 552.58721 | Q92: =P92/I92 -> 0.58785874 | V92: 2 | W92: 0 | X92: 0 | Y92: 0 | Z92: 0
A93: BUCKMAN | B93: LS-002467 | C93: WOODMERE ST - 4211 | D93: 3 | F93: 181.95949 | G93: 1 | H93: 457.09096 | I93: 1400 | J93: 2 | K93: 0.32649354 | M93: 0.0066181576 | N93: 1 | O93: =F93*(1+M93)^10 -> 194.3669 | P93: =(18+SQRT(O93/100))/(4+SQRT(O93/100))*O93*1000/1440 -> 485.29659 | Q93: =P93/I93 -> 0.34664042 | V93: 2 | W93: 1 | X93: 0 | Y93: 0 | Z93: 0
A94: CEDAR BAY | B94: LS-001027 | C94: HARTS RD - 11305 | D94: 4 | F94: 3482.6292 | G94: 1 | H94: 5838.1061 | I94: 4190 | J94: 2 | K94: 1.3933427 | M94: 0.046020689 | N94: 1 | O94: =F94*(1+M94)^10 -> 5461.4754 | P94: =(18+SQRT(O94/100))/(4+SQRT(O94/100))*O94*1000/1440 -> 8454.3981 | Q94: =P94/I94 -> 2.0177561 | S94: 180-26 | T94: 2025 | V94: 2 | W94: 2 | X94: 1 | Y94: 1 | Z94: 0
A95: CEDAR BAY | B95: LS-001192 | C95: KEY HAVEN BV - 10800 | D95: 3 | F95: 624.54107 | G95: 1 | H95: 1367.9837 | I95: 1090 | J95: 2 | K95: 1.2550309 | M95: 0.030649903 | N95: 1 | O95: =F95*(1+M95)^10 -> 844.64199 | P95: =(18+SQRT(O95/100))/(4+SQRT(O95/100))*O95*1000/1440 -> 1775.5916 | Q95: =P95/I95 -> 1.6289831 | S95: 180-46 | T95: 2025 | V95: 2 | W95: 1 | X95: 0 | Y95: 1 | Z95: 0
A96: CEDAR BAY | B96: LS-001817 | C96: PULASKI RD - 12321 | D96: 4 | F96: 1233.2609 | G96: 1 | H96: 2452.5953 | I96: 4790 | J96: 2 | K96: 0.51202407 | M96: 0.03232581 | N96: 1 | O96: =F96*(1+M96)^10 -> 1695.2073 | P96: =(18+SQRT(O96/100))/(4+SQRT(O96/100))*O96*1000/1440 -> 3207.6072 | Q96: =P96/I96 -> 0.6696466 | S96: 180-40 | T96: 2028 | V96: 3 | W96: 1 | X96: 0 | Y96: 1 | Z96: 0
A97: CEDAR BAY | B97: LS-000768 | C97: DUVAL RD - 14491 | D97: 4 | F97: 825.18539 | G97: 1 | H97: 1740.3811 | I97: 2300 | J97: 2 | K97: 0.75668742 | M97: 0.0763205 | N97: 3 | O97: =F97*(1+M97)^10 -> 1721.7403 | P97: =(18+SQRT(O97/100))/(4+SQRT(O97/100))*O97*1000/1440 -> 3249.6902 | Q97: =P97/I97 -> 1.4129088 | S97: 139-02 | T97: 2029 | V97: 3 | W97: 1 | X97: 0 | Y97: 1 | Z97: 0
A98: CEDAR BAY | B98: LS-000598 | C98: COLE FLYER RD - 2111 | D98: 3 | F98: 182.1311 | G98: 1 | H98: 457.4827 | I98: 1190 | J98: 2 | K98: 0.38443924 | M98: 0.02232239 | N98: 1 | O98: =F98*(1+M98)^10 -> 227.1239 | P98: =(18+SQRT(O98/100))/(4+SQRT(O98/100))*O98*1000/1440 -> 558.69165 | Q98: =P98/I98 -> 0.46948878 | V98: 3 | W98: 1 | X98: 0 | Y98: 1 | Z98: 0
A99: CEDAR BAY | B99: LS-000851 | C99: ETHEL RD - 16536 | D99: 3 | F99: 2 | G99: 3 | H99: 6.0840027 | I99: 770 | J99: 2 | K99: 0.0079013022 | M99: 0 | N99: 2 | O99: =F99*(1+M99)^10 -> 2 | P99: =(18+SQRT(O99/100))/(4+SQRT(O99/100))*O99*1000/1440 -> 6.0840027 | Q99: =P99/I99 -> 0.0079013022 | V99: 3 | W99: 1 | X99: 0 | Y99: 1 | Z99: 0
A100: CEDAR BAY | B100: LS-003967 | C100: MAX LEGGETT PY - 15171 | D100: 3 | F100: 44.6 | G100: 2 | H100: 123.9 | I100: 652.09274 | J100: 1 | K100: 0.19000365 | M100: 0.05 | N100: 2 | O100: =F100*(1+M100)^10 -> 72.6487 | P100: =(18+SQRT(O100/100))/(4+SQRT(O100/100))*O100*1000/1440 -> 196.01047 | Q100: =P100/I100 -> 0.30058679 | V100: 2 | W100: 1 | X100: 0 | Y100: 0 | Z100: 0
A101: CEDAR BAY | B101: LS-001441 | C101: MENLO AV - 1410 | D101: 4 | F101: 249.38462 | G101: 1 | H101: 607.75796 | I101: 1490 | J101: 2 | K101: 0.40789125 | M101: 0.0026485215 | N101: 1 | O101: =F101*(1+M101)^10 -> 256.0689 | P101: =(18+SQRT(O101/100))/(4+SQRT(O101/100))*O101*1000/1440 -> 622.37261 | Q101: =P101/I101 -> 0.41769974 | V101: 3 | W101: 1 | X101: 0 | Y101: 1 | Z101: 0
A102: CEDAR BAY | B102: LS-001857 | C102: RENNE DR W - 11452 | D102: 3 | F102: 381.25587 | G102: 1 | H102: 887.45839 | I102: 1200 | J102: 2 | K102: =H102/I102 -> 0.73954865 | M102: 0.02 | N102: 2 | O102: =F102*(1+M102)^10 -> 464.74878 | P102: =(18+SQRT(O102/100))/(4+SQRT(O102/100))*O102*1000/1440 -> 1056.7473 | Q102: =P102/I102 -> 0.88062274 | V102: 3 | W102: 1 | X102: 0 | Y102: 1 | Z102: 0
A103: MANDARIN | B103: LS-000235 | C103: BARTRAM PARK BV - 12882 | D103: 3 | F103: 352.23629 | G103: 1 | H103: 827.32734 | I103: 2120 | J103: 2 | K103: 0.39024874 | M103: 0.016266427 | N103: 1 | O103: =F103*(1+M103)^10 -> 413.91378 | P103: =(18+SQRT(O103/100))/(4+SQRT(O103/100))*O103*1000/1440 -> 954.30074 | Q103: =P103/I103 -> 0.45014186 | V103: 3 | W103: 1 | X103: 0 | Y103: 1 | Z103: 0
A104: MANDARIN | B104: LS-000237 | C104: BARTRAM PARK BV - 14041 | D104: 4 | F104: 103 | G104: 3 | H104: 271.21093 | I104: 1040 | J104: 2 | K104: 0.26077974 | M104: 0.08951623 | N104: 1 | O104: =F104*(1+M104)^10 -> 242.7584 | P104: =(18+SQRT(O104/100))/(4+SQRT(O104/100))*O104*1000/1440 -> 593.21718 | Q104: =P104/I104 -> 0.57040114 | V104: 3 | W104: 1 | X104: 0 | Y104: 1 | Z104: 0
A105: MANDARIN | B105: LS-003356 | C105: BARTRAM PARK BV - 14802 | D105: 3 | F105: 42.94334 | G105: 1 | H105: 119.50527 | I105: 1140 | J105: 2 | K105: 0.10482919 | M105: 0.11105708 | N105: 1 | O105: =F105*(1+M105)^10 -> 123.10041 | P105: =(18+SQRT(O105/100))/(4+SQRT(O105/100))*O105*1000/1440 -> 319.71834 | Q105: =P105/I105 -> 0.28045469 | V105: 3 | W105: 1 | X105: 0 | Y105: 0 | Z105: 0
A106: MANDARIN | B106: LS-000263 | C106: BAYOU BLUFF DR - 9733 | D106: 3 | F106: 578.95363 | G106: 1 | H106: 1280.6943 | I106: 1760 | J106: 2 | K106: 0.7276672 | M106: 0.028893814 | N106: 1 | O106: =F106*(1+M106)^10 -> 769.74937 | P106: =(18+SQRT(O106/100))/(4+SQRT(O106/100))*O106*1000/1440 -> 1639.2416 | Q106: =P106/I106 -> 0.93138726 | V106: 3 | W106: 1 | X106: 0 | Y106: 0 | Z106: 0
A107: MANDARIN | B107: LS-000465 | C107: BRIERWOOD RD - 8460 | D107: 3 | F107: 258.71035 | G107: 1 | H107: 628.13336 | I107: 870 | J107: 2 | K107: 0.72199237 | M107: 0.0078026568 | N107: 1 | O107: =F107*(1+M107)^10 -> 279.62036 | P107: =(18+SQRT(O107/100))/(4+SQRT(O107/100))*O107*1000/1440 -> 673.45487 | Q107: =P107/I107 -> 0.77408606 | V107: 3 | W107: 1 | X107: 0 | Y107: 1 | Z107: 0
A108: MANDARIN | B108: LS-000630 | C108: CORKLAN DR - 7250 | D108: 3 | F108: 446.48688 | G108: 1 | H108: 1020.1581 | I108: 1890 | J108: 2 | K108: 0.53976621 | M108: 0.068333416 | N108: 1 | O108: =F108*(1+M108)^10 -> 864.72264 | P108: =(18+SQRT(O108/100))/(4+SQRT(O108/100))*O108*1000/1440 -> 1811.7812 | Q108: =P108/I108 -> 0.95861438 | S108: * | V108: 3 | W108: 1 | X108: 0 | Y108: 1 | Z108: 0
A109: MANDARIN | B109: BPS-004153 | C109: ENERGY CENTER DR - 6850 | D109: 4 | F109: 166.464 | G109: 4 | H109: 421.52362 | I109: 1200 | J109: 2 | K109: 0.35126969 | M109: 0.05 | N109: 2 | O109: =F109*(1+M109)^10 -> 271.15232 | P109: =(18+SQRT(O109/100))/(4+SQRT(O109/100))*O109*1000/1440 -> 655.15996 | Q109: =P109/I109 -> 0.54596664 | V109: 3 | W109: 1 | X109: 1 | Y109: 1 | Z109: 1
A110: MANDARIN | B110: LS-000951 | C110: GINNIE SPRINGS RD - 6350 | D110: 4 | F110: 278.46985 | G110: 1 | H110: 670.97386 | I110: 1100 | J110: 2 | K110: 0.60997624 | M110: 0.00029320966 | N110: 1 | O110: =F110*(1+M110)^10 -> 279.28743 | P110: =(18+SQRT(O110/100))/(4+SQRT(O110/100))*O110*1000/1440 -> 672.73707 | Q110: =P110/I110 -> 0.61157915 | V110: 2 | W110: 1 | X110: 0 | Y110: 1 | Z110: 0
A111: MANDARIN | B111: LS-001178 | C111: KENNEDY LA - 10656 | D111: 3 | F111: 328.64336 | G111: 1 | H111: 777.89339 | I111: 1500 | J111: 2 | K111: =H111/I111 -> 0.51859559 | M111: 0.03 | N111: 2 | O111: =F111*(1+M111)^10 -> 441.66919 | P111: =(18+SQRT(O111/100))/(4+SQRT(O111/100))*O111*1000/1440 -> 1010.4664 | Q111: =P111/I111 -> 0.67364426 | V111: 3 | W111: 1 | X111: 0 | Y111: 1 | Z111: 0
A112: MANDARIN | B112: BPS-001645 | C112: OLDFIELD CROSSING DR - 4193 | D112: 4 | F112: 2714.5385 | G112: 4 | H112: 4750.5677 | I112: 9370 | J112: 2 | K112: 0.50699762 | M112: 0.03863988 | N112: 1 | O112: =F112*(1+M112)^10 -> 3965.9382 | P112: =(18+SQRT(O112/100))/(4+SQRT(O112/100))*O112*1000/1440 -> 6498.4765 | Q112: =P112/I112 -> 0.69354071 | V112: 4 | W112: 2 | X112: 1 | Y112: 1 | Z112: 1
A113: MANDARIN | B113: LS-001647 | C113: ORANGE PICKER RD - 2520 | D113: 3 | F113: 313.18831 | G113: 1 | H113: 745.2281 | I113: 1370 | J113: 2 | K113: 0.54396211 | M113: 0.060960455 | N113: 1 | O113: =F113*(1+M113)^10 -> 565.97534 | P113: =(18+SQRT(O113/100))/(4+SQRT(O113/100))*O113*1000/1440 -> 1255.6372 | Q113: =P113/I113 -> 0.91652352 | V113: 3 | W113: 1 | X113: 0 | Y113: 1 | Z113: 0
A114: MANDARIN | B114: LS-002154 | C114: ST AUGUSTINE RD - 11220 | D114: 3 | F114: 227.75339 | G114: 1 | H114: 560.08779 | I114: 2400 | J114: 2 | K114: 0.23336991 | M114: 0.0065410531 | N114: 1 | O114: =F114*(1+M114)^10 -> 243.0971 | P114: =(18+SQRT(O114/100))/(4+SQRT(O114/100))*O114*1000/1440 -> 593.96174 | Q114: =P114/I114 -> 0.24748406 | V114: 3 | W114: 1 | X114: 0 | Y114: 1 | Z114: 0
A115: MONTEREY | B115: LS-002295 | C115: TOWNSEND BV - 3254 | D115: 3 | F115: 404.22679 | G115: 2 | H115: 934.56166 | I115: 700 | J115: 2 | K115: 1.3350881 | M115: 0.01241998 | N115: 1 | O115: =F115*(1+M115)^10 -> 457.33261 | P115: =(18+SQRT(O115/100))/(4+SQRT(O115/100))*O115*1000/1440 -> 1041.9164 | Q115: =P115/I115 -> 1.488452 | S115: 180-59 | T115: 2025 | V115: 3 | W115: 2 | X115: 0 | Y115: 0 | Z115: 0
A116: MONTEREY | B116: LS-001452 | C116: MERRILL RD - 7732 | D116: 3 | F116: 263.26753 | G116: 1 | H116: 638.05308 | I116: 720 | J116: 2 | K116: 0.88618483 | M116: 0.0078453023 | N116: 1 | O116: =F116*(1+M116)^10 -> 284.6663 | P116: =(18+SQRT(O116/100))/(4+SQRT(O116/100))*O116*1000/1440 -> 684.31917 | Q116: =P116/I116 -> 0.9504433 | S116: 180-61 | T116: 2026 | V116: 2 | W116: 1 | X116: 0 | Y116: 1 | Z116: 0
...

Sheet piwebapi_90d
A1: cmms | B1: adf_kGPD | C1: phf_gpm
A2: LS-000550 | B2: 131.29719 | C2: 252.0902
A3: LS-002144 | B3: 0.11117275 | C3: 13.941855
A4: LS-000813 | B4: 0.15356611 | C4: 227.91013
A5: LS-003704 | B5: 0.20328535 | C5: 58.329711
A6: LS-002143 | B6: 0.24837129 | C6: 54.101283
A7: LS-001564 | B7: 0.27064438 | C7: 15.462294
A8: LS-000656 | B8: 0.29507934 | C8: 7.3561859
A9: LS-004101 | B9: 0.37024167 | C9: 11.330883
A10: LS-001870 | B10: 0.39873164 | C10: 99.94141
A11: LS-001462 | B11: 0.42895099 | C11: 98.317884
A12: LS-003714 | B12: 0.4311926 | C12: 376.56859
A13: LS-004060 | B13: 0.51633584 | C13: 164.28453
... A1471: LS-001423 | B1471: 2310.4918 | C1471: 1643.761
